Workbook

Sheet Kangatang

Sheet PL03a
A2: BẢNG XÁC ĐỊNH GIÁ TRỊ KHỐI LƯỢNG CÔNG VIỆC HOÀN THÀNH THANH TOÁN LẦN THỨ: LẦN 01
A4: STT | B4: Tên công việc | C4: Đơn vị tính | D4: Quy cách kỹ thuật | E4: Thương hiệu | F4: Khối lượng | G4: Đơn giá
F5: Khối lượng theo hợp đồng
H6: Ghi chú
A7: 22 | B7: THIẾT BỊ ĐIỆN NHẸ
A8: 22.1 | B8: Hệ thống mạng - phần thiết bị
A9: 22.1.1 | B9: Core switch 24 SFP | C9: bộ | D9: ICX 7550 24 port | E9: Ruckus | F9: 1
A10: 22.1.2 | B10: Bộ máy tính server | C10: bộ | E10: Dell | F10: 1
A11: 22.1.3 | B11: Router Load balance | C11: bộ | D11: BLP-70 | E11: Ruckus | F11: 1
A12: 22.1.4 | B12: WIFI CONTROLLER | C12: bộ | D12: P01-S144-UK00 S02-S144-3000 377*L09-0001-SG00 377*S02-0001-3LSG | E12: Ruckus | F12: 1
A13: 22.2 | B13: Hệ thống mạng
A14: 22.2.1 | B14: Wifi gắn tường | C14: bộ | D14: RUIJIE REYEE RG-RAP2200€ | E14: Ruijie | F14: 274
A15: 22.2.2 | B15: Wifi âm trần | C15: bộ | D15: Bộ phát Wifi Ruijie Reyee RG-RAP6260(G) AX1800 Wi-Fi 6 Dual | E15: Ruijie | F15: 63
A16: 22.2.3 | B16: Switch poe 6p cổng RJ45 10/100/100 | C16: chiếc | D16: Switch POE 6 cổng 10/100/1000BASE-T Ruijie Reyee RG-ES206GC-P | E16: Ruijie | F16: 3
A17: 22.2.4 | B17: Switch poe 8p cổng RJ45 10/100/100 | C17: chiếc | D17: Switch 8 cổng 10/100/1000 BASE-T RUIJIE RG-NBS3100-8GT2SFP | E17: Ruijie | F17: 1
A18: 22.2.5 | B18: Switch poe 12p cổng RJ45 10/100/100 | C18: chiếc | D18: ICX7150-C12P-2X1G | E18: Ruckus | F18: 3
A19: 22.2.6 | B19: Switch poe 24p cổng RJ45 10/100/100 | C19: chiếc | D19: ICX8200-24P | E19: Ruckus | F19: 12
A20: 22.2.7 | B20: Switch 4p cổng RJ45 10/100/100 | C20: chiếc | D20: Switch POE 4 cổng RUIJIE REYEE RG-ES205GC-P | E20: Ruijie | F20: 1
A21: 22.2.8 | B21: Switch 6p cổng RJ45 10/100/100 | C21: chiếc | D21: Switch POE 6 cổng 10/100/1000BASE-T Ruijie Reyee RG-ES206GC-P | E21: Ruijie | F21: 2
A22: 22.2.9 | B22: Switch 8p cổng RJ45 10/100/100 | C22: chiếc | D22: Switch 8 cổng 10/100/1000 BASE-T RUIJIE RG-NBS3100-8GT2SFP | E22: Ruijie | F22: 1
A23: 22.2.10 | B23: Switch 12p cổng RJ45 10/100/100 | C23: chiếc | D23: ICX7150-C12P-2X1G | E23: Ruckus | F23: 2
A24: 22.2.11 | B24: Switch 24p cổng RJ45 10/100/100 | C24: chiếc | D24: ICX7150-24-4X1G | E24: Ruckus | F24: 13
A25: 22.2.12 | B25: Patch Panel 4p | C25: chiếc | E25: Legrand | F25: 1
A26: 22.2.13 | B26: Patch Panel 6p | C26: chiếc | E26: Legrand | F26: 5
A27: 22.2.14 | B27: Patch Panel 8p | C27: chiếc | E27: Legrand | F27: 2
A28: 22.2.15 | B28: Patch Panel 12p | C28: chiếc | E28: Legrand | F28: 4
A29: 22.2.16 | B29: Patch Panel 24p | C29: chiếc | E29: Legrand | F29: 25
A30: 22.3 | B30: HỆ THỐNG ĐIỆN THOẠI - PHẦN THIẾT BỊ
A31: 22.3.1 | B31: Tổng đài điện thoại IP 30 trung kế số, 128 máy tính | C31: bộ | D31: Tổng đài Yeastar MyPBX S300 | E31: Yeastar | F31: 3
A32: 22.3.2 | B32: Điện thoại IP Phone Sử dụng cho việc lập trình phím bấm, hiển thị cuộc gọi | C32: Chiếc | D32: Điện thoại IP Yealink SIP-T53W | E32: Yealink | F32: 1
A33: 22.3.3 | B33: Phần mềm tính cước (Thống kê cước nội bộ, thống kế theo số máy lẻ và nhóm người dùng; Lọc các cuộc gọi theo thời gian linh hoạt; Thực hiện hiệu chỉnh để phù hợp với giá cước của Bưu điện và Tổng đài; Phân quyền sử dụng và quản trị). | C33: License | D33: Yeastar S50 | E33: YEASTAR | F33: 1
A34: 22.3.4 | B34: Máy in cước laser đen trắng. Khổ giấy: A4/A5. In đảo mặt: Không. Cổng giao tiếp: USB/ LAN | C34: bộ | D34: HL-L2321D Máy in Laser | E34: Laser | F34: 1
A35: 22.4 | B35: HỆ THỐNG CAMERA GIÁM SÁT AN NINH - PHẦN THIẾT BỊ
A36: 22.4.1 | B36: Camera dome hồng ngoại 4Megapixe | C36: bộ | D36: Camera IP 4MP Dome DAHUA DH-IPC-HDW2441T-S | E36: Dahua | F36: 104
A37: 22.4.2 | B37: Camera thân hồng ngoại 4Megapixe | C37: bộ | D37: Camera IP thân trụ 4MP DAHUA DH-IPC-HFW2441TP-ZS | E37: Dahua | F37: 8
A38: 22.4.3 | B38: Camera Speeddome 2.0 Megapixel (OUR DOOR/ INDOOR) | C38: bộ | D38: Camera IP Speed Dome 2MP DAHUA DH-SD49225DB-HNY | F38: 12
A39: 22.4.4 | B39: Đầu ghi hình 32 kênh camera IP 1.5U 4HDD và phụ kiện | C39: bộ | D39: Đầu ghi hình IP 32 kênh DAHUA DHI-NVR5432-EI | F39: 6
A40: 22.4.5 | B40: Ổ cứng chuyên dụng 6TB 3.5", 64Mb Cache, SATA 3,hỗ trợ RAID, hoạt động 24/7 | C40: chiếc | D40: Ổ cứng gắn trong SEAGATE HDD SkyHawk 6TB, 5400 RPM, Cache 256MB (ST6000VX009) | F40: 6
A41: 22.4.6 | B41: Màn hình hiển thị camera Full HD 49" kèm giá treo tường | C41: chiếc | D41: Màn hình quảng cáo LG 50UL3J | F41: 6
A42: 22.4.7 | B42: Bộ máy chủ 21" | C42: bộ | E42: Dell | F42: 1
A43: 22.4.8 | B43: Bộ phân nguồn | C43: bộ | D43: Ổ Cắm Lọc Điện Clef PowerBRIDGE - 8 | F43: 1
A44: 22.5 | B44: HỆ THỐNG CAMERA GIÁM SÁT AN NINH - PHẦN VẬT TƯ
A45: 22.5.1 | B45: Switch core 16 ports | C45: chiếc | D45: ICX-8200-24P | E45: Ruckus | F45: 1
A46: 22.5.2 | B46: Switch poe 24 ports | C46: chiếc | D46: ICX-8200-24FX ICX-8200-PREM-LIC | E46: Ruckus | F46: 6
A47: 22.5.3 | B47: Switch poe 16 ports | C47: chiếc | D47: ICX-8200-24P | E47: Ruckus | F47: 3
A48: 22.6 | B48: HỆ THỐNG ÂM THANH CÔNG CỘNG - PHẦN THIẾT BỊ
A49: 22.6.1 | B49: Bộ điều khiển trung tâm 8 vùng | C49: chiếc | D49: Bộ xử lý trung tâm 8 vùng Honeywell HCU-2000 | F49: 2
A50: 22.6.2 | B50: Bộ mở rộng 8 vùng | C50: chiếc | D50: Bộ mở rộng 8 vùng Honeywell HEX-8 | F50: 2
A51: 22.6.3 | B51: Micro chọn vùng | C51: chiếc | D51: Micro chọn vùng Honeywell HMC-2000 | F51: 1
A52: 22.6.4 | B52: Bàn phím mở rộng 8 vùng | C52: chiếc | D52: Bàn phím mở rộng 8 vùng Honeywell HMC-K8 | F52: 1
A53: 22.6.5 | B53: Đầu phát nhạc nền | C53: chiếc | D53: XMAP4P | E53: Honeywell | F53: 1
A54: 22.6.6 | B54: Bộ khuếch đại công suất 500W | C54: chiếc | D54: Bộ khuếch đại công suất 500W Honeywell HAM-2000 | F54: 4
A55: 22.6.7 | B55: Loa trần 6W | C55: chiếc | D55: Loa âm trần 6W/3W/1.5W Honeywell HN-CL06 | F55: 252
A56: 22.6.8 | B56: Loa hộp 6W | C56: chiếc | D56: Loa hộp 6W/3W Honeywell L-PWP06B | F56: 26
A57: 22.6.9 | B57: Loa nén 15W | C57: chiếc | D57: Loa còi 15W/7.5W Honeywell L-PHP15A | F57: 4
A58: 22.7 | B58: HỆ THỐNG KÍCH SÓNG ĐIỆN THOẠI - PHẦN THIẾT BỊ
A59: 22.7.1 | B59: Aten gắn trần | C59: chiếc | D59: IXD-360V03NP-DC | E59: Comba | F59: 114
A60: 22.7.2 | B60: Anten gắn tường | C60: chiếc | D60: PM-AS-IWH-979 V10NBJ-KT | E60: Comba | F60: 8
A61: 22.7.3 | B61: Bộ trộn tín hiệu | C61: bộ | D61: POI-CD62IDN1VN | E61: Comba | F61: 1
A62: 22.7.4 | B62: Bộ chia 2 | C62: bộ | D62: PS-R2-ON500C(H) | E62: Comba | F62: 2
A63: 22.7.5 | B63: Bộ chia 3 | C63: bộ | D63: PS-R3-ON500C(H) | E63: Comba | F63: 15
A64: 22.7.6 | B64: Bộ chia 4 | C64: bộ | D64: PS-R4-ON500C(H) | E64: Comba | F64: 30
A65: 22.8 | B65: HỆ THỐNG QUẢN LÍ XE RA VÀO
A66: 22.8.1 | B66: Đầu đọc thẻ khoảng cách xa | C66: bộ | D66: UHF2-10E | E66: Ztekco | F66: 2
A67: 22.8.2 | B67: Đầu đọc thẻ khoảng cách gần | C67: bộ | D67: MR101 | E67: Ztekco | F67: 2
A68: 22.8.3 | B68: Vòng loop kích hoạt đóng/mở barrier | C68: bộ | D68: Bộ dò vòng từ PD132 | E68: Bisen | F68: 2
A69: 22.8.4 | B69: Barrier chắn xe lối vào/ra | C69: bộ | D69: Barrier tự động Road RD-101T | F69: 2
A70: 22.8.5 | B70: Bộ điều khiển chính | C70: bộ | E70: VN | F70: 2
A71: 22.8.6 | B71: UPS 2kVA | C71: bộ | D71: 310171 | E71: Legrand | F71: 1
A72: 22.8.7 | B72: Camera nhận dạng biển số xe máy | C72: bộ | D72: NST-IPA6092-NPSD | E72: Enster | F72: 2
A73: 22.8.8 | B73: Camera nhận dạng biển số ô tô | C73: bộ | D73: NST-IPA6092-NPSD | E73: Enster | F73: 2
A74: 22.8.9 | B74: Camera chụp toàn cảnh | C74: bộ | D74: NST-IPH5842S | E74: Enster | F74: 2
A75: 22.8.10 | B75: Switch POE 8 cổng RJ45 10/100/100 | C75: bộ | D75: TSW200 | E75: Teltonika | F75: 2
A76: 22.8.11 | B76: Switch 24 cổng RJ45 10/100/100 | C76: bộ | D76: ICX7150-24-4X1G Ruckus ICX 7150 24 Ports Switch with 1 GBE Uplinks | F76: 1
A77: 22.8.12 | B77: Module chuyển đổi quang điện SFP | C77: bộ | D77: Converter quang G-NET HHD-220G-20 tốc độ 10/100/1000 | F77: 4
A78: 22.8.13 | B78: Máy tính cài phền mềm quản lý xe ra/vào | C78: bộ | D78: OptiPlex 3090 Tower 4GB | E78: Dell | F78: 1
A79: 22.8.14 | B79: Cáp quang 2FO | C79: m | F79: 50
A80: 22.9 | B80: HỆ THỐNG ÂM THANH HỘI HỌP PHÒNG HỘI NGHỊ ĐA NĂNG
A81: 22.9.1 | B81: Micro cổ ngỗng để bục 450mm | C81: bộ | D81: Micro cổ ngỗng đơn hướng Shure MX418D/C | F81: 1
A82: 22.9.2 | B82: Micro Dynamic dùng cho Ca sĩ và ban nhạc | C82: bộ | D82: SHURE SM58 | F82: 2
A83: 22.9.3 | B83: Micro Dynamic không dây UHF cầm tay | C83: bộ | D83: Bộ micro không dây SLX24A/SM58 | F83: 2
A84: 22.9.4 | B84: Micro không dây UHF cài áo | C84: bộ | D84: MICRO SHURE SLXD14A/85 | F84: 2
A85: 22.9.5 | B85: UHF Antenna 470MHz - 875MHz | C85: chiếc | D85: UA864LO | E85: Shure | F85: 2
A86: 22.10 | B86: HỆ THỐNG ÂM THANH BIỂU DIỄN CHUYÊN NGHIỆP
A87: 22.10.1 | B87: Loa biểu diễn 90°x50°, 600W/2300W 132dB | C87: bộ | D87: Loa toàn dải two-way Electro-Voice ZX5-60B (W) | F87: 10
A88: 22.10.2 | B88: Loa toàn dải sân khấu 1500W, 134dB | C88: bộ | D88: Loa toàn dải 4 tấc công suất EV EKX-15P | F88: 4
A89: 22.10.3 | B89: Loa siêu trầm 18" 1300W, 134dB | C89: bộ | D89: Loa Sub 5 tấc công suất EV EKX-18SP | F89: 4
A90: 22.10.4 | B90: Khuếch đại công suất có DSP 2x1400W@4Ω | C90: bộ | D90: Cục đẩy công suất Dynacord C2800FDI | F90: 3
A91: 22.10.5 | B91: Bàn trộn âm thanh 22 đường, có hiệu ứng | C91: bộ | D91: Mixer Dynacord CMS 2200-3 | F91: 1
A92: 22.10.6 | B92: Bộ xử lý âm thanh kỹ thuật số 2:6 ngõ vào:ra | C92: bộ | D92: Bộ xử lý tín hiệu âm thanh DBX DriveRack 260 | F92: 1
A93: 22.10.7 | B93: Bộ nén và kiểm soát tín hiệu âm thanh | C93: bộ | D93: DBX 1046 | F93: 1
A94: 22.10.8 | B94: Bộ lọc và cân bằng tần số âm thanh ra loa | C94: bộ | D94: DBX 2231 | F94: 1
A95: 22.10.9 | B95: Bộ lọc nhiễu tín hiệu âm thanh và chống hú | C95: bộ | D95: DBX AFS2 : Bộ xử lý phản hồi âm thanh | F95: 1
A96: 22.10.10 | B96: Bộ lọc nhiễu âm thanh cho nhạc cụ điện tử | C96: bộ | D96: Bộ điều chỉnh tần số DBX Db12 | F96: 4
A97: 22.10.11 | B97: Bộ tạo hiệu ứng âm thanh cho ca sĩ | C97: bộ | D97: Bộ xử lý âm thanh Yamaha SPX2000 | F97: 1
A98: 22.10.12 | B98: Chân Micro cao 1600mm | C98: bộ | D98: DD085 | E98: Soundking | F98: 3
A99: 22.11 | B99: HỆ THỐNG MÁY CHIẾU HÌNH ĐỘ NÉT CAO (DÙNG CHO HỘI NGHỊ)
A100: 22.11.1 | B100: Màn hình LED trong nhà 7650 x 4150mm | C100: Gói | D100: LED P3 Trong nhà GKGD | F100: 1
A101: 22.11.2 | B101: Màn hình LED Backlit, tấm nền IPS 86", Full HD (1920x1080) | C101: bộ | D101: 86UL5J-H | F101: 2
A102: 22.12 | B102: ÁNH SÁNG SÂN KHẤU
...

Sheet Sheet2
B3: HĐ | C3: tạm ứng lần 1 | D3: tạm ứng lần 2 | E3: Ttlần 1 | F3: tổng tiền đã nhận
A4: Tân Khánh hoà | B4: =PL03a!#REF! -> #REF! | C4: =H6-D4 -> #REF! | D4: 42388366000 | E4: =PL03a!#REF! -> #REF! | F4: =C4+D4+E4 -> #REF!
A5: Đường bộ | B5: 3469422000 | C5: =ROUND(B5*0.3,-3) -> 1040827000 | D5: =ROUND(B5*0.2,-3) -> 693884000 | E5: 1199602000 | F5: =C5+D5+E5 -> 2934313000
A6: Đường bộ - mua sắm | B6: 37512999000 | C6: 18756499000 | F6: =C6+D6+E6 -> 18756499000 | H6: =PL03a!#REF! -> #REF!
A7: tổng cộng | B7: =SUM(B4:B6) -> #REF! | C7: =SUM(C4:C6) -> #REF! | D7: =SUM(D4:D6) -> 43082250000 | E7: =SUM(E4:E6) -> #REF! | F7: =SUM(F4:F6) -> #REF!

Sheet Sheet1
K7: Khánh Hòa, ngày tháng năm 20
C9: ĐẠI DIỆN ĐƠN VỊ THI CÔNG | K9: ĐẠI DIỆN CHỦ ĐẦU TƯ
A11: Công ty TNHH Tân Khánh Hòa KH | F11: Công ty TNHH Cơ điện Khánh Hòa
A18: Công ty cổ phần Quản lý và Xây dựng đường bộ Khánh Hòa | F18: Công ty cổ phần Cơ điện lạnh Đông Sapa
K30: Khánh Hòa, ngày tháng năm 20
B32: ĐẠI DIỆN ĐƠN VỊ THI CÔNG | K32: ĐẠI DIỆN CHỦ ĐẦU TƯ

Sheet BBNTHT
A2: CỘNG HÒA XÃ HỘI CHỦ NGHĨA VIỆT NAM
A3: Độc lập - Tự do - Hạnh phúc
D4: Khánh Hòa, ngày …... tháng …..năm 2024.
A5: BIÊN BẢN NGHIỆM THU KHỐI LƯỢNG HOÀN THÀNH ĐỢT 1
A7: Gói thầu: Thi công xây dựng toàn bộ các hạng mục công trình và lắp đặt thiết bị trạm biến áp 1.600KVA, máy phát điện dự phòng 670KVA, hệ thống điện nhẹ, hệ thống điều hòa thông gió, hệ thống PCCC, máy bơm nước sinh hoạt, hệ thống nước nóng
A8: Dự án: Nhà khách Công an tỉnh Khánh Hòa
A9: Địa điểm: 78 Tuệ Tĩnh, phường Lộc Thọ, thành phố Nha Trang, Khánh Hòa
A11: I. THÀNH PHẦN THAM GIA NGHIỆM THU:
A12: 1. Đại diện Chủ đầu tư: Công an tỉnh Khánh Hòa
B13: - Ông: Nguyễn Văn Ngàn | C13: Chức vụ: Phó giám đốc
B14: - Ông: Đường Trung Thành | C14: Chức vụ: Trưởng phòng PH10
B15: - Ông: Lương Duy Quốc Tuấn | C15: Chức vụ: Đội trưởng đội XD-ĐT phòng PH10
A16: 2. Đại diện Tư vấn Quản lý dự án: Công ty Cổ phần Tư vấn Quản lý dự án Việt Nam
B17: - Ông: Nguyễn Cảnh Tiến | C17: Chức vụ: Giám đốc Công ty
B18: - Ông: Nguyễn Văn Nam | C18: Chức vụ: PGĐ QLDA
A19: 3. Đại diện đơn vị giám sát: Công ty Cổ phần Coninco – Thăng Long
B20: - Ông: Đặng Văn Bắc | C20: Chức vụ: Phó tổng giám đốc
B21: - Ông: Đặng Thái Sơn | C21: Chức vụ: Giám sát trưởng
B22: - Ông: Ngô Chí | C22: Chức vụ: CB Giám sát
B23: - Ông: | C23: Chức vụ: CB Giám sát
A24: 4. Đại diện đơn vị thi công: Liên danh thi công Nhà khách CA tỉnh Khánh Hòa
A25: 4.1 | B25: Thành viên Liên danh: Công ty TNHH Tân Khánh Hòa KH
B26: - Ông: Võ Đình Khang | C26: Chức vụ: Giám đốc
B27: - Ông: Huỳnh Tấn Khánh | C27: Chức vụ: Chỉ huy trưởng
A28: 4.2 | B28: Thành viên Liên danh: Công ty TNHH Cơ điện Khánh Hòa
B29: - Ông: Trương Sỹ Trường | C29: Chức vụ: Giám đốc
B30: - Ông: | C30: Chức vụ: Chỉ huy trưởng
A31: 4.3 | B31: Thành viên Liên danh: Công ty cổ phần Quản lý và Xây dựng đường bộ Khánh Hòa
B32: - Ông: Lê Thuận Đoàn | C32: Chức vụ: Giám đốc
B33: - Ông: | C33: Chức vụ: Chỉ huy trưởng
A34: 4.4 | B34: Thành viên Liên danh: Công ty cổ phần Cơ điện lạnh Đông Sapa
B35: - Ông: Nguyễn Phú Hữu | C35: Chức vụ: Giám đốc
B36: - Ông: | C36: Chức vụ: Chỉ huy trưởng
A37: II. THỜI GIAN NGHIỆM THU:
B38: - Bắt đầu : 08 giờ 00 phút, ngày….. tháng…...năm 2024.
B39: - Kết thúc: 10 giờ 30 phút, ngày….. tháng ….năm 2024.
B40: - Địa điểm: Tại công trình thi công.
A41: III. ĐÁNH GIÁ CÔNG VIỆC XÂY DỰNG ĐÃ THỰC HIỆN:
A42: 1. Về tài liệu làm căn cứ nghiệm thu:
A43: 1. Về tài liệu làm căn cứ nghiệm thu:
A44: Căn cứ Hợp đồng số 2706/2024/HĐXD ngày 27 tháng 06 năm 2024,Phụ lục Hợp đồng số 2706A/2024/HĐXD ngày 06 tháng 11 năm 2024 và Phụ lục Hợp đồng số 2706B/2024/HĐXD ngày 12 tháng 12 năm 2024 v/v thực hiện thi công Gói thầu XL01: Thi công xây dựng toàn bộ các hạng mục công trình và lắp đặt thiết bị trạm biến áp 1.600KVA, máy phát điện dự phòng 500KVA, hệ thống điện nhẹ, hệ thống điều hòa thông gió, hệ thống PCCC, máy bơm nước sinh hoạt, hệ thống nước nóng thuộc dự án "Nhà khách Công an tỉnh Khánh Hòa";
A45: - Căn cứ hồ sơ thiết kế, hồ sơ dự thầu đã được phê duyệt;
A46: - Căn cứ nhật ký thi công, nhật ký giám sát của TVGS và các văn bản khác có liên quan đến đối tượng nghiệm thu;
A47: - Căn cứ bản vẽ hoàn công hạng mục nghiệm thu;
A48: 2. Về chất lượng công trình:
B49: - Kiểm tra đối tượng nghiệm thu tại hiện trường; đạt yêu cầu
A50: 3. Về khối lượng công việc thực hiện:
B51: - Khối lượng thực hiện: Theo Bảng diễn giải khối lượng hoàn thành đính kèm.
B52: * Sau khi kiểm tra, hội đồng thống nhất nghiệm thu khối lượng xây lắp hoàn thành đợt 01 của Liên danh thi công Nhà khách Công an tỉnh Khánh Hòa thực hiện:
A53: STT | B53: Tên công việc | C53: Đơn vị | D53: Khối lượng | S53: Ghi chú
D54: Theo hợp đồng | E54: Nghiệm thu thực tế | L54: Đề nghị thanh toán
E55: Lũy kế đến hết kỳ trước | F55: Thực hiện kỳ này Công ty TNHH Tân Khánh Hòa KH | G55: Thực hiện kỳ này Công ty TNHH Cơ điện Khánh Hòa | H55: Thực hiện kỳ này công ty CP QL và XD Đường bộ KH | I55: Thực hiện kỳ này Công ty Cơ điện lạnh Đông Sapa | J55: Lũy kế đến hết kỳ này | K55: Chênh lệch so với hợp đồng | L55: Lũy kế đến hết kỳ trước | M55: =F55 -> Thực hiện kỳ này Công ty TNHH Tân Khánh Hòa KH | N55: =G55 -> Thực hiện kỳ này Công ty TNHH Cơ điện Khánh Hòa | O55: =H55 -> Thực hiện kỳ này công ty CP QL và XD Đường bộ KH | P55: =I55 -> Thực hiện kỳ này Công ty Cơ điện lạnh Đông Sapa | Q55: Lũy kế thanh toán đến hết kỳ này | R55: Chênh lệch so với hợp đồng
A56: 1 | B56: PHẦN CỌC
A57: 1.1 | B57: Cọc PHC D600 Class A | C57: m | D57: 6556.9 | F57: =D57*0.9 -> 5901.21 | J57: =F57+G57+H57+I57 -> 5901.21 | K57: =J57-D57 -> -655.69 | M57: =F57 -> 5901.21 | N57: =G57 -> 0 | O57: =H57 -> 0 | P57: =I57 -> 0 | Q57: =M57+N57+O57+P57 -> 5901.21 | R57: =Q57-D57 -> -655.69
A58: 1.2 | B58: Mũi cọc | C58: cái | D58: 203 | F58: =D58 -> 203 | J58: =F58+G58+H58+I58 -> 203 | K58: =J58-D58 -> 0 | M58: =F58 -> 203 | N58: =G58 -> 0 | O58: =H58 -> 0 | P58: =I58 -> 0 | Q58: =M58+N58+O58+P58 -> 203 | R58: =Q58-D58 -> 0
A59: 1.3 | B59: Khoan dẫn phục vụ đóng, ép cọc bằng máy khoan xoay, đường kính 400mm | C59: m | D59: 2892.75 | F59: =D59*0.75 -> 2169.5625 | J59: =F59+G59+H59+I59 -> 2169.5625 | K59: =J59-D59 -> -723.1875 | M59: =F59 -> 2169.5625 | N59: =G59 -> 0 | O59: =H59 -> 0 | P59: =I59 -> 0 | Q59: =M59+N59+O59+P59 -> 2169.5625 | R59: =Q59-D59 -> -723.1875
A60: 1.4 | B60: Ép cọc ống bê tông cốt thép dự ứng lực bằng máy ép Robot thủy lực tự hành, đất cấp I, đường kính cọc 600mm | C60: 100m | D60: 57.631 | F60: =D60*0.75 -> 43.22325 | J60: =F60+G60+H60+I60 -> 43.22325 | K60: =J60-D60 -> -14.40775 | M60: =F60 -> 43.22325 | N60: =G60 -> 0 | O60: =H60 -> 0 | P60: =I60 -> 0 | Q60: =M60+N60+O60+P60 -> 43.22325 | R60: =Q60-D60 -> -14.40775
A61: 1.5 | B61: Ép cọc ống bê tông cốt thép dự ứng lực bằng máy ép Robot thủy lực tự hành, đất cấp I, đường kính cọc 600mm, đoạn cọc không ngập đất | C61: 100m | D61: 0.006 | J61: =F61+G61+H61+I61 -> 0 | K61: =J61-D61 -> -0.006 | M61: =F61 -> 0 | N61: =G61 -> 0 | O61: =H61 -> 0 | P61: =I61 -> 0 | Q61: =M61+N61+O61+P61 -> 0 | R61: =Q61-D61 -> -0.006
A62: 1.6 | B62: Ép cọc ống bê tông cốt thép dự ứng lực bằng máy ép Robot thủy lực tự hành , đất cấp I, đường kính cọc 600mm, ép âm sử dụng cọc dẫn | C62: 100m | D62: 6.729 | J62: =F62+G62+H62+I62 -> 0 | K62: =J62-D62 -> -6.729 | M62: =F62 -> 0 | N62: =G62 -> 0 | O62: =H62 -> 0 | P62: =I62 -> 0 | Q62: =M62+N62+O62+P62 -> 0 | R62: =Q62-D62 -> -6.729
A63: 1.7 | B63: Nối cọc ống bê tông cốt thép, đường kính cọc <= 600mm | C63: mối nối | D63: 203 | J63: =F63+G63+H63+I63 -> 0 | K63: =J63-D63 -> -203 | M63: =F63 -> 0 | N63: =G63 -> 0 | O63: =H63 -> 0 | P63: =I63 -> 0 | Q63: =M63+N63+O63+P63 -> 0 | R63: =Q63-D63 -> -203
A64: 1.8 | B64: Cắt đầu cọc | C64: mối | D64: 203 | J64: =F64+G64+H64+I64 -> 0 | K64: =J64-D64 -> -203 | M64: =F64 -> 0 | N64: =G64 -> 0 | O64: =H64 -> 0 | P64: =I64 -> 0 | Q64: =M64+N64+O64+P64 -> 0 | R64: =Q64-D64 -> -203
A65: 1.9 | B65: Vận chuyển đất bằng ôtô tự đổ trong phạm vi <= 1000m, đất cấp III | C65: 100m3 | D65: 0.344 | J65: =F65+G65+H65+I65 -> 0 | K65: =J65-D65 -> -0.344 | M65: =F65 -> 0 | N65: =G65 -> 0 | O65: =H65 -> 0 | P65: =I65 -> 0 | Q65: =M65+N65+O65+P65 -> 0 | R65: =Q65-D65 -> -0.344
A66: 1.10 | B66: Vận chuyển đất bằng ô tô tự đổ 1km tiếp theo ngoài phạm vi 5km, đất cấp III | C66: 100m3 | D66: 0.344 | J66: =F66+G66+H66+I66 -> 0 | K66: =J66-D66 -> -0.344 | M66: =F66 -> 0 | N66: =G66 -> 0 | O66: =H66 -> 0 | P66: =I66 -> 0 | Q66: =M66+N66+O66+P66 -> 0 | R66: =Q66-D66 -> -0.344
A67: 1.11 | B67: Gia công cấu kiện thép đặt sẵn trong bê tông, khối lượng một cấu kiện <= 50 kg | C67: tấn | D67: 9.354 | J67: =F67+G67+H67+I67 -> 0 | K67: =J67-D67 -> -9.354 | M67: =F67 -> 0 | N67: =G67 -> 0 | O67: =H67 -> 0 | P67: =I67 -> 0 | Q67: =M67+N67+O67+P67 -> 0 | R67: =Q67-D67 -> -9.354
A68: 1.12 | B68: Lắp đặt cấu kiện thép đặt sẵn trong bê tông, khối lượng một cấu kiện <= 50 kg | C68: tấn | D68: 9.354 | J68: =F68+G68+H68+I68 -> 0 | K68: =J68-D68 -> -9.354 | M68: =F68 -> 0 | N68: =G68 -> 0 | O68: =H68 -> 0 | P68: =I68 -> 0 | Q68: =M68+N68+O68+P68 -> 0 | R68: =Q68-D68 -> -9.354
A69: 1.13 | B69: Đổ bê tông thủ công bằng máy trộn, bê tông móng, chiều rộng <= 250 cm, đá 1x2, mác 300 | C69: m3 | D69: 53.409 | J69: =F69+G69+H69+I69 -> 0 | K69: =J69-D69 -> -53.409 | M69: =F69 -> 0 | N69: =G69 -> 0 | O69: =H69 -> 0 | P69: =I69 -> 0 | Q69: =M69+N69+O69+P69 -> 0 | R69: =Q69-D69 -> -53.409
A70: 2 | B70: PHẦN DƯỚI CỐT 0.0M | J70: =F70+G70+H70+I70 -> 0 | K70: =J70-D70 -> 0 | M70: =F70 -> 0 | N70: =G70 -> 0 | O70: =H70 -> 0 | P70: =I70 -> 0 | Q70: =M70+N70+O70+P70 -> 0 | R70: =Q70-D70 -> 0
A71: 2.1 | B71: Đào móng công trình, chiều rộng móng ≤6m, bằng máy đào, đất cấp II | C71: 100m3 | D71: 48.676 | J71: =F71+G71+H71+I71 -> 0 | K71: =J71-D71 -> -48.676 | M71: =F71 -> 0 | N71: =G71 -> 0 | O71: =H71 -> 0 | P71: =I71 -> 0 | Q71: =M71+N71+O71+P71 -> 0 | R71: =Q71-D71 -> -48.676 | U71: 0.62
A72: 2.2 | B72: Đắp đất công trình bằng đầm đất cầm tay, độ chặt yêu cầu K=0,85 | C72: 100m3 | D72: 1.31 | J72: =F72+G72+H72+I72 -> 0 | K72: =J72-D72 -> -1.31 | M72: =F72 -> 0 | N72: =G72 -> 0 | O72: =H72 -> 0 | P72: =I72 -> 0 | Q72: =M72+N72+O72+P72 -> 0 | R72: =Q72-D72 -> -1.31
A73: 2.3 | B73: Vận chuyển đất bằng ôtô tự đổ trong phạm vi ≤1000m, đất cấp II | C73: 100m3 | D73: 47.235 | J73: =F73+G73+H73+I73 -> 0 | K73: =J73-D73 -> -47.235 | M73: =F73 -> 0 | N73: =G73 -> 0 | O73: =H73 -> 0 | P73: =I73 -> 0 | Q73: =M73+N73+O73+P73 -> 0 | R73: =Q73-D73 -> -47.235
A74: 2.4 | B74: Vận chuyển đất bằng ô tô tự đổ 1km tiếp theo trong phạm vi ≤5km, đất cấp II | C74: 100m3 | D74: 47.235 | J74: =F74+G74+H74+I74 -> 0 | K74: =J74-D74 -> -47.235 | M74: =F74 -> 0 | N74: =G74 -> 0 | O74: =H74 -> 0 | P74: =I74 -> 0 | Q74: =M74+N74+O74+P74 -> 0 | R74: =Q74-D74 -> -47.235
A75: 2.5 | B75: Bê tông lót móng, chiều rộng ≤250cm, đá 4x6, mác 100 | C75: m3 | D75: 157.661 | J75: =F75+G75+H75+I75 -> 0 | K75: =J75-D75 -> -157.661 | M75: =F75 -> 0 | N75: =G75 -> 0 | O75: =H75 -> 0 | P75: =I75 -> 0 | Q75: =M75+N75+O75+P75 -> 0 | R75: =Q75-D75 -> -157.661
A76: 2.6 | B76: Lớp màng chống thấm tự dính dày 2mm | C76: m2 | D76: 875.73 | J76: =F76+G76+H76+I76 -> 0 | K76: =J76-D76 -> -875.73 | M76: =F76 -> 0 | N76: =G76 -> 0 | O76: =H76 -> 0 | P76: =I76 -> 0 | Q76: =M76+N76+O76+P76 -> 0 | R76: =Q76-D76 -> -875.73
A77: 2.7 | B77: Láng nền sàn không đánh mầu,vữa XM mác 50 | C77: m2 | D77: 875.73 | J77: =F77+G77+H77+I77 -> 0 | K77: =J77-D77 -> -875.73 | M77: =F77 -> 0 | N77: =G77 -> 0 | O77: =H77 -> 0 | P77: =I77 -> 0 | Q77: =M77+N77+O77+P77 -> 0 | R77: =Q77-D77 -> -875.73
A78: 2.8 | B78: Đổ bê tông bằng máy, đổ bằng máy bơm bê tông, bê tông móng, chiều rộng móng ≤250cm, đá 1x2, mác 400 | C78: m3 | D78: 9.075 | J78: =F78+G78+H78+I78 -> 0 | K78: =J78-D78 -> -9.075 | M78: =F78 -> 0 | N78: =G78 -> 0 | O78: =H78 -> 0 | P78: =I78 -> 0 | Q78: =M78+N78+O78+P78 -> 0 | R78: =Q78-D78 -> -9.075
A79: 2.9 | B79: Đổ bê tông bằng máy, đổ bằng máy bơm bê tông, bê tông móng, chiều rộng móng >250cm, đá 1x2, mác 400 | C79: m3 | D79: 1025.075 | J79: =F79+G79+H79+I79 -> 0 | K79: =J79-D79 -> -1025.075 | M79: =F79 -> 0 | N79: =G79 -> 0 | O79: =H79 -> 0 | P79: =I79 -> 0 | Q79: =M79+N79+O79+P79 -> 0 | R79: =Q79-D79 -> -1025.075
A80: 2.10 | B80: Ván khuôn móng cột | C80: 100m2 | D80: 8.564 | J80: =F80+G80+H80+I80 -> 0 | K80: =J80-D80 -> -8.564 | M80: =F80 -> 0 | N80: =G80 -> 0 | O80: =H80 -> 0 | P80: =I80 -> 0 | Q80: =M80+N80+O80+P80 -> 0 | R80: =Q80-D80 -> -8.564
A81: 2.11 | B81: Cốt thép móng, D≤10mm | C81: tấn | D81: 0.01 | F81: =D81*$U$71 -> 0.0062 | J81: =F81+G81+H81+I81 -> 0.0062 | K81: =J81-D81 -> -0.0038 | M81: =F81 -> 0.0062 | N81: =G81 -> 0 | O81: =H81 -> 0 | P81: =I81 -> 0 | Q81: =M81+N81+O81+P81 -> 0.0062 | R81: =Q81-D81 -> -0.0038
A82: 2.12 | B82: Cốt thép móng, D≤18mm | C82: tấn | D82: 21.879 | F82: =D82*$U$71 -> 13.56498 | J82: =F82+G82+H82+I82 -> 13.56498 | K82: =J82-D82 -> -8.31402 | M82: =F82 -> 13.56498 | N82: =G82 -> 0 | O82: =H82 -> 0 | P82: =I82 -> 0 | Q82: =M82+N82+O82+P82 -> 13.56498 | R82: =Q82-D82 -> -8.31402
A83: 2.13 | B83: Cốt thép móng, D>18mm | C83: tấn | D83: 29.372 | F83: =D83*$U$71 -> 18.21064 | J83: =F83+G83+H83+I83 -> 18.21064 | K83: =J83-D83 -> -11.16136 | M83: =F83 -> 18.21064 | N83: =G83 -> 0 | O83: =H83 -> 0 | P83: =I83 -> 0 | Q83: =M83+N83+O83+P83 -> 18.21064 | R83: =Q83-D83 -> -11.16136
A84: 2.14 | B84: Đổ bê tông bằng máy, đổ bằng máy bơm bê tông, bê tông dầm móng, đá 1x2, mác 400 | C84: m3 | D84: 73.314 | J84: =F84+G84+H84+I84 -> 0 | K84: =J84-D84 -> -73.314 | M84: =F84 -> 0 | N84: =G84 -> 0 | O84: =H84 -> 0 | P84: =I84 -> 0 | Q84: =M84+N84+O84+P84 -> 0 | R84: =Q84-D84 -> -73.314
A85: 2.15 | B85: Ván khuôn dầm móng | C85: 100m2 | D85: 2.789 | J85: =F85+G85+H85+I85 -> 0 | K85: =J85-D85 -> -2.789 | M85: =F85 -> 0 | N85: =G85 -> 0 | O85: =H85 -> 0 | P85: =I85 -> 0 | Q85: =M85+N85+O85+P85 -> 0 | R85: =Q85-D85 -> -2.789
A86: 2.16 | B86: Cốt thép dầm móng, D≤10mm | C86: tấn | D86: 3.217 | F86: =D86*$U$71 -> 1.99454 | J86: =F86+G86+H86+I86 -> 1.99454 | K86: =J86-D86 -> -1.22246 | M86: =F86 -> 1.99454 | N86: =G86 -> 0 | O86: =H86 -> 0 | P86: =I86 -> 0 | Q86: =M86+N86+O86+P86 -> 1.99454 | R86: =Q86-D86 -> -1.22246
A87: 2.17 | B87: Cốt thép dầm móng, D≤18mm | C87: tấn | D87: 2.771 | F87: =D87*$U$71 -> 1.71802 | J87: =F87+G87+H87+I87 -> 1.71802 | K87: =J87-D87 -> -1.05298 | M87: =F87 -> 1.71802 | N87: =G87 -> 0 | O87: =H87 -> 0 | P87: =I87 -> 0 | Q87: =M87+N87+O87+P87 -> 1.71802 | R87: =Q87-D87 -> -1.05298
A88: 2.18 | B88: Cốt thép dầm móng, D>18mm | C88: tấn | D88: 12.622 | F88: =D88*$U$71 -> 7.82564 | J88: =F88+G88+H88+I88 -> 7.82564 | K88: =J88-D88 -> -4.79636 | M88: =F88 -> 7.82564 | N88: =G88 -> 0 | O88: =H88 -> 0 | P88: =I88 -> 0 | Q88: =M88+N88+O88+P88 -> 7.82564 | R88: =Q88-D88 -> -4.79636
A89: 2.19 | B89: Đổ bê tông bằng máy, đổ bằng máy bơm bê tông, bê tông sàn hầm, chiều rộng >250cm, đá 1x2, mác 400 | C89: m3 | D89: 288.082 | J89: =F89+G89+H89+I89 -> 0 | K89: =J89-D89 -> -288.082 | M89: =F89 -> 0 | N89: =G89 -> 0 | O89: =H89 -> 0 | P89: =I89 -> 0 | Q89: =M89+N89+O89+P89 -> 0 | R89: =Q89-D89 -> -288.082
A90: 2.20 | B90: Đổ bê tông đúc sẵn bằng thủ công - sản xuất bằng máy trộn. Bê tông tấm đan, đá 1x2, mác 200 | C90: m3 | D90: 0.629 | J90: =F90+G90+H90+I90 -> 0 | K90: =J90-D90 -> -0.629 | M90: =F90 -> 0 | N90: =G90 -> 0 | O90: =H90 -> 0 | P90: =I90 -> 0 | Q90: =M90+N90+O90+P90 -> 0 | R90: =Q90-D90 -> -0.629
A91: 2.21 | B91: Công tác gia công, lắp dựng, tháo dỡ ván khuôn. Ván khuôn thép, ván khuôn nắp đan | C91: 100m2 | D91: 0.02 | J91: =F91+G91+H91+I91 -> 0 | K91: =J91-D91 -> -0.02 | M91: =F91 -> 0 | N91: =G91 -> 0 | O91: =H91 -> 0 | P91: =I91 -> 0 | Q91: =M91+N91+O91+P91 -> 0 | R91: =Q91-D91 -> -0.02
A92: 2.22 | B92: Lắp các loại cấu kiện bê tông đúc sẵn bằng thủ công, trọng lượng ≤75kg | C92: 1 cấu kiện | D92: 4 | J92: =F92+G92+H92+I92 -> 0 | K92: =J92-D92 -> -4 | M92: =F92 -> 0 | N92: =G92 -> 0 | O92: =H92 -> 0 | P92: =I92 -> 0 | Q92: =M92+N92+O92+P92 -> 0 | R92: =Q92-D92 -> -4
A93: 2.23 | B93: Lắp đặt cấu kiện bê tông đúc sẵn trọng lượng >50kg-200kg bằng cần cẩu | C93: 1 cấu kiện | D93: 3 | J93: =F93+G93+H93+I93 -> 0 | K93: =J93-D93 -> -3 | M93: =F93 -> 0 | N93: =G93 -> 0 | O93: =H93 -> 0 | P93: =I93 -> 0 | Q93: =M93+N93+O93+P93 -> 0 | R93: =Q93-D93 -> -3
A94: 2.24 | B94: Cốt thép sàn hầm, D≤10mm | C94: tấn | D94: 0.027 | F94: =D94*$U$71 -> 0.01674 | J94: =F94+G94+H94+I94 -> 0.01674 | K94: =J94-D94 -> -0.01026 | M94: =F94 -> 0.01674 | N94: =G94 -> 0 | O94: =H94 -> 0 | P94: =I94 -> 0 | Q94: =M94+N94+O94+P94 -> 0.01674 | R94: =Q94-D94 -> -0.01026
A95: 2.25 | B95: Cốt thép sàn hầm, D≤18mm | C95: tấn | D95: 31.126 | F95: =D95*$U$71 -> 19.29812 | J95: =F95+G95+H95+I95 -> 19.29812 | K95: =J95-D95 -> -11.82788 | M95: =F95 -> 19.29812 | N95: =G95 -> 0 | O95: =H95 -> 0 | P95: =I95 -> 0 | Q95: =M95+N95+O95+P95 -> 19.29812 | R95: =Q95-D95 -> -11.82788
A96: 2.26 | B96: Đổ bê tông bằng máy, đổ bằng máy bơm bê tông, bê tông tường, chiều dày ≤45cm, chiều cao ≤6m, đá 1x2, mác 400 | C96: m3 | D96: 94.891 | J96: =F96+G96+H96+I96 -> 0 | K96: =J96-D96 -> -94.891 | M96: =F96 -> 0 | N96: =G96 -> 0 | O96: =H96 -> 0 | P96: =I96 -> 0 | Q96: =M96+N96+O96+P96 -> 0 | R96: =Q96-D96 -> -94.891
A97: 2.27 | B97: Ván khuôn tường, chiều cao ≤28m | C97: 100m2 | D97: 6.287 | J97: =F97+G97+H97+I97 -> 0 | K97: =J97-D97 -> -6.287 | M97: =F97 -> 0 | N97: =G97 -> 0 | O97: =H97 -> 0 | P97: =I97 -> 0 | Q97: =M97+N97+O97+P97 -> 0 | R97: =Q97-D97 -> -6.287
A98: 2.28 | B98: Cốt thép tường, D≤10mm, chiều cao ≤6m | C98: tấn | D98: 6.492 | F98: =D98*$U$71 -> 4.02504 | J98: =F98+G98+H98+I98 -> 4.02504 | K98: =J98-D98 -> -2.46696 | M98: =F98 -> 4.02504 | N98: =G98 -> 0 | O98: =H98 -> 0 | P98: =I98 -> 0 | Q98: =M98+N98+O98+P98 -> 4.02504 | R98: =Q98-D98 -> -2.46696
A99: 2.29 | B99: Cốt thép tường, D≤18mm, chiều cao ≤6m | C99: tấn | D99: 0.116 | F99: =D99*$U$71 -> 0.07192 | J99: =F99+G99+H99+I99 -> 0.07192 | K99: =J99-D99 -> -0.04408 | M99: =F99 -> 0.07192 | N99: =G99 -> 0 | O99: =H99 -> 0 | P99: =I99 -> 0 | Q99: =M99+N99+O99+P99 -> 0.07192 | R99: =Q99-D99 -> -0.04408
A100: 2.30 | B100: Đổ bê tông bằng máy, đổ bằng máy bơm bê tông, bê tông tường, chiều dày ≤45cm, chiều cao ≤6m, đá 1x2, mác 500 | C100: m3 | D100: 72.237 | J100: =F100+G100+H100+I100 -> 0 | K100: =J100-D100 -> -72.237 | M100: =F100 -> 0 | N100: =G100 -> 0 | O100: =H100 -> 0 | P100: =I100 -> 0 | Q100: =M100+N100+O100+P100 -> 0 | R100: =Q100-D100 -> -72.237
A101: 2.31 | B101: Ván khuôn bằng ván ép phủ phim có khung xương, cột chống bằng hệ giáo ống. Ván khuôn tường, chiều cao ≤28m | C101: 100m2 | D101: 4.244 | J101: =F101+G101+H101+I101 -> 0 | K101: =J101-D101 -> -4.244 | M101: =F101 -> 0 | N101: =G101 -> 0 | O101: =H101 -> 0 | P101: =I101 -> 0 | Q101: =M101+N101+O101+P101 -> 0 | R101: =Q101-D101 -> -4.244
A102: 2.32 | B102: Đổ bê tông bằng máy, đổ bằng máy bơm bê tông, bê tông cột, tiết diện cột >0,1m2, chiều cao ≤6m, đá 1x2, mác 400 | C102: m3 | D102: 59.064 | J102: =F102+G102+H102+I102 -> 0 | K102: =J102-D102 -> -59.064 | M102: =F102 -> 0 | N102: =G102 -> 0 | O102: =H102 -> 0 | P102: =I102 -> 0 | Q102: =M102+N102+O102+P102 -> 0 | R102: =Q102-D102 -> -59.064
A103: 2.33 | B103: Ván khuôn bằng ván ép phủ phim, khung thép hình, dàn giáo công cụ kết hợp cột chống bằng hệ giáo ống. Ván khuôn cột vuông, chữ nhật, chiều cao ≤28m | C103: 100m2 | D103: 2.297 | J103: =F103+G103+H103+I103 -> 0 | K103: =J103-D103 -> -2.297 | M103: =F103 -> 0 | N103: =G103 -> 0 | O103: =H103 -> 0 | P103: =I103 -> 0 | Q103: =M103+N103+O103+P103 -> 0 | R103: =Q103-D103 -> -2.297
...

Sheet PL 03 liên danh
L1: Mẫu số 03a/TT
A2: BẢNG XÁC ĐỊNH GIÁ TRỊ KHỐI LƯỢNG CÔNG VIỆC HOÀN THÀNH THANH TOÁN LẦN THỨ: LẦN 01
A3: Tên dự án: Nhà khách Công an tỉnh Khánh Hòa; Mã dự án: 7004692
A4: Tên gói thầu XL01: Hợp đồng thi công xây dựng công trình
A5: Căn cứ hợp đồng số: 2706/2024/HĐXD ngày 27 tháng 6 năm 2024; Phụ lục Hợp đồng số 2706A/2024/HĐXD ngày 06/11/2024 ; Phụ lục Hợp đồng số 2706B/2024/HĐXD ngày….../12/2024 và Phụ lục Hợp đồng số 2706C/2024/HĐXD ngày ….../12/2024
A6: Căn cứ Quyết định phê duyệt dự toán số (trong trường hợp thực hiện không thông qua hợp đồng):…..ngày tháng năm 2024
A7: Chủ đầu tư: Công an tỉnh Khánh Hoà
A8: Nhà thầu: Liên danh thi công nhà khách Công an tỉnh Khánh Hoà
A9: Thanh toán lần thứ: 01 ( Phần khối lượng do liên danh thi công Nhà khách Công an tỉnh Khánh Hòa thực hiện)
A10: Căn cứ xác định:
A11: Biên bản nghiệm thu khối lượng hoàn thành đợt 01 ngày…… tháng …. .năm 2024.
L12: Đơn vị: Đồng
A13: STT | B13: Tên công việc | C13: Đơn vị tính | D13: Khối lượng | H13: Đơn giá thanh toán theo hợp đồng | I13: Thành tiền
D14: Khối lượng theo hợp đồng | E14: Thực hiện | I14: =D14 -> Khối lượng theo hợp đồng | J14: Thực hiện
E15: Lũy kế đến hết kỳ trước | F15: Thực hiện kỳ này | G15: Lũy kế đến hết kỳ này | J15: =E15 -> Lũy kế đến hết kỳ trước | K15: Thực hiện kỳ này | L15: =G15 -> Lũy kế đến hết kỳ này | M15: Ghi chú
A16: 1 | B16: PHẦN CỌC
A17: 1.1 | B17: Cọc PHC D600 Class A | C17: m | D17: 6556.9 | F17: =BBNTHT!J57 -> 5901.21 | G17: =F17+E17 -> 5901.21 | H17: 1092176 | I17: =ROUND(D17*H17,0) -> 7161288814 | K17: =ROUND(F17*H17,0) -> 6445159933 | L17: =J17+K17 -> 6445159933
A18: 1.2 | B18: Mũi cọc | C18: cái | D18: 203 | F18: =BBNTHT!J58 -> 203 | G18: =F18+E18 -> 203 | H18: 304794 | I18: =ROUND(D18*H18,0) -> 61873182 | K18: =ROUND(F18*H18,0) -> 61873182 | L18: =J18+K18 -> 61873182
A19: 1.3 | B19: Khoan dẫn phục vụ đóng, ép cọc bằng máy khoan xoay, đường kính 400mm | C19: m | D19: 2892.75 | F19: =BBNTHT!J59 -> 2169.5625 | G19: =F19+E19 -> 2169.5625 | H19: 1009270 | I19: =ROUND(D19*H19,0) -> 2919565793 | K19: =ROUND(F19*H19,0) -> 2189674344 | L19: =J19+K19 -> 2189674344
A20: 1.4 | B20: Ép cọc ống bê tông cốt thép dự ứng lực bằng máy ép Robot thủy lực tự hành, đất cấp I, đường kính cọc 600mm | C20: 100m | D20: 57.631 | F20: =BBNTHT!J60 -> 43.22325 | G20: =F20+E20 -> 43.22325 | H20: 23523671 | I20: =ROUND(D20*H20,0) -> 1355692683 | K20: =ROUND(F20*H20,0) -> 1016769513 | L20: =J20+K20 -> 1016769513
A21: 1.5 | B21: Ép cọc ống bê tông cốt thép dự ứng lực bằng máy ép Robot thủy lực tự hành, đất cấp I, đường kính cọc 600mm, đoạn cọc không ngập đất | C21: 100m | D21: 0.006 | F21: =BBNTHT!J61 -> 0 | G21: =F21+E21 -> 0 | H21: 17642753 | I21: =ROUND(D21*H21,0) -> 105857 | K21: =ROUND(F21*H21,0) -> 0 | L21: =J21+K21 -> 0
A22: 1.6 | B22: Ép cọc ống bê tông cốt thép dự ứng lực bằng máy ép Robot thủy lực tự hành , đất cấp I, đường kính cọc 600mm, ép âm sử dụng cọc dẫn | C22: 100m | D22: 6.729 | F22: =BBNTHT!J62 -> 0 | G22: =F22+E22 -> 0 | H22: 24699855 | I22: =ROUND(D22*H22,0) -> 166205324 | K22: =ROUND(F22*H22,0) -> 0 | L22: =J22+K22 -> 0
A23: 1.7 | B23: Nối cọc ống bê tông cốt thép, đường kính cọc <= 600mm | C23: mối nối | D23: 203 | F23: =BBNTHT!J63 -> 0 | G23: =F23+E23 -> 0 | H23: 622096 | I23: =ROUND(D23*H23,0) -> 126285488 | K23: =ROUND(F23*H23,0) -> 0 | L23: =J23+K23 -> 0
A24: 1.8 | B24: Cắt đầu cọc | C24: mối | D24: 203 | F24: =BBNTHT!J64 -> 0 | G24: =F24+E24 -> 0 | H24: 281360 | I24: =ROUND(D24*H24,0) -> 57116080 | K24: =ROUND(F24*H24,0) -> 0 | L24: =J24+K24 -> 0
A25: 1.9 | B25: Vận chuyển đất bằng ôtô tự đổ trong phạm vi <= 1000m, đất cấp III | C25: 100m3 | D25: 0.344 | F25: =BBNTHT!J65 -> 0 | G25: =F25+E25 -> 0 | H25: 3030140 | I25: =ROUND(D25*H25,0) -> 1042368 | K25: =ROUND(F25*H25,0) -> 0 | L25: =J25+K25 -> 0
A26: 1.10 | B26: Vận chuyển đất bằng ô tô tự đổ 1km tiếp theo ngoài phạm vi 5km, đất cấp III | C26: 100m3 | D26: 0.344 | F26: =BBNTHT!J66 -> 0 | G26: =F26+E26 -> 0 | H26: 3561537 | I26: =ROUND(D26*H26,0) -> 1225169 | K26: =ROUND(F26*H26,0) -> 0 | L26: =J26+K26 -> 0
A27: 1.11 | B27: Gia công cấu kiện thép đặt sẵn trong bê tông, khối lượng một cấu kiện <= 50 kg | C27: tấn | D27: 9.354 | F27: =BBNTHT!J67 -> 0 | G27: =F27+E27 -> 0 | H27: 38704566 | I27: =ROUND(D27*H27,0) -> 362042510 | K27: =ROUND(F27*H27,0) -> 0 | L27: =J27+K27 -> 0
A28: 1.12 | B28: Lắp đặt cấu kiện thép đặt sẵn trong bê tông, khối lượng một cấu kiện <= 50 kg | C28: tấn | D28: 9.354 | F28: =BBNTHT!J68 -> 0 | G28: =F28+E28 -> 0 | H28: 5407084 | I28: =ROUND(D28*H28,0) -> 50577864 | K28: =ROUND(F28*H28,0) -> 0 | L28: =J28+K28 -> 0
A29: 1.13 | B29: Đổ bê tông thủ công bằng máy trộn, bê tông móng, chiều rộng <= 250 cm, đá 1x2, mác 300 | C29: m3 | D29: 53.409 | F29: =BBNTHT!J69 -> 0 | G29: =F29+E29 -> 0 | H29: 1703602 | I29: =ROUND(D29*H29,0) -> 90987679 | K29: =ROUND(F29*H29,0) -> 0 | L29: =J29+K29 -> 0
A30: 2 | B30: PHẦN DƯỚI CỐT 0.0M | F30: =BBNTHT!J70 -> 0 | G30: =F30+E30 -> 0 | K30: =ROUND(F30*H30,0) -> 0 | L30: =J30+K30 -> 0
A31: 2.1 | B31: Đào móng công trình, chiều rộng móng ≤6m, bằng máy đào, đất cấp II | C31: 100m3 | D31: 48.676 | F31: =BBNTHT!J71 -> 0 | G31: =F31+E31 -> 0 | H31: 2235933 | I31: =ROUND(D31*H31,0) -> 108836275 | K31: =ROUND(F31*H31,0) -> 0 | L31: =J31+K31 -> 0
A32: 2.2 | B32: Đắp đất công trình bằng đầm đất cầm tay, độ chặt yêu cầu K=0,85 | C32: 100m3 | D32: 1.31 | F32: =BBNTHT!J72 -> 0 | G32: =F32+E32 -> 0 | H32: 3013626 | I32: =ROUND(D32*H32,0) -> 3947850 | K32: =ROUND(F32*H32,0) -> 0 | L32: =J32+K32 -> 0
A33: 2.3 | B33: Vận chuyển đất bằng ôtô tự đổ trong phạm vi ≤1000m, đất cấp II | C33: 100m3 | D33: 47.235 | F33: =BBNTHT!J73 -> 0 | G33: =F33+E33 -> 0 | H33: 2359400 | I33: =ROUND(D33*H33,0) -> 111446259 | K33: =ROUND(F33*H33,0) -> 0 | L33: =J33+K33 -> 0
A34: 2.4 | B34: Vận chuyển đất bằng ô tô tự đổ 1km tiếp theo trong phạm vi ≤5km, đất cấp II | C34: 100m3 | D34: 47.235 | F34: =BBNTHT!J74 -> 0 | G34: =F34+E34 -> 0 | H34: 4024442 | I34: =ROUND(D34*H34,0) -> 190094518 | K34: =ROUND(F34*H34,0) -> 0 | L34: =J34+K34 -> 0
A35: 2.5 | B35: Bê tông lót móng, chiều rộng ≤250cm, đá 4x6, mác 100 | C35: m3 | D35: 157.661 | F35: =BBNTHT!J75 -> 0 | G35: =F35+E35 -> 0 | H35: 1223510 | I35: =ROUND(D35*H35,0) -> 192899810 | K35: =ROUND(F35*H35,0) -> 0 | L35: =J35+K35 -> 0
A36: 2.6 | B36: Lớp màng chống thấm tự dính dày 2mm | C36: m2 | D36: 875.73 | F36: =BBNTHT!J76 -> 0 | G36: =F36+E36 -> 0 | H36: 190495 | I36: =ROUND(D36*H36,0) -> 166822186 | K36: =ROUND(F36*H36,0) -> 0 | L36: =J36+K36 -> 0
A37: 2.7 | B37: Láng nền sàn không đánh mầu,vữa XM mác 50 | C37: m2 | D37: 875.73 | F37: =BBNTHT!J77 -> 0 | G37: =F37+E37 -> 0 | H37: 45008 | I37: =ROUND(D37*H37,0) -> 39414856 | K37: =ROUND(F37*H37,0) -> 0 | L37: =J37+K37 -> 0
A38: 2.8 | B38: Đổ bê tông bằng máy, đổ bằng máy bơm bê tông, bê tông móng, chiều rộng móng ≤250cm, đá 1x2, mác 400 | C38: m3 | D38: 9.075 | F38: =BBNTHT!J78 -> 0 | G38: =F38+E38 -> 0 | H38: 2243046 | I38: =ROUND(D38*H38,0) -> 20355642 | K38: =ROUND(F38*H38,0) -> 0 | L38: =J38+K38 -> 0
A39: 2.9 | B39: Đổ bê tông bằng máy, đổ bằng máy bơm bê tông, bê tông móng, chiều rộng móng >250cm, đá 1x2, mác 400 | C39: m3 | D39: 1025.075 | F39: =BBNTHT!J79 -> 0 | G39: =F39+E39 -> 0 | H39: 2343243 | I39: =ROUND(D39*H39,0) -> 2401999818 | K39: =ROUND(F39*H39,0) -> 0 | L39: =J39+K39 -> 0
A40: 2.10 | B40: Ván khuôn móng cột | C40: 100m2 | D40: 8.564 | F40: =BBNTHT!J80 -> 0 | G40: =F40+E40 -> 0 | H40: 12390253 | I40: =ROUND(D40*H40,0) -> 106110127 | K40: =ROUND(F40*H40,0) -> 0 | L40: =J40+K40 -> 0
A41: 2.11 | B41: Cốt thép móng, D≤10mm | C41: tấn | D41: 0.01 | F41: =BBNTHT!J81 -> 0.0062 | G41: =F41+E41 -> 0.0062 | H41: 24189690 | I41: =ROUND(D41*H41,0) -> 241897 | K41: =ROUND(F41*H41,0) -> 149976 | L41: =J41+K41 -> 149976
A42: 2.12 | B42: Cốt thép móng, D≤18mm | C42: tấn | D42: 21.879 | F42: =BBNTHT!J82 -> 13.56498 | G42: =F42+E42 -> 13.56498 | H42: 24758906 | I42: =ROUND(D42*H42,0) -> 541700104 | K42: =ROUND(F42*H42,0) -> 335854065 | L42: =J42+K42 -> 335854065
... A103: 2.73 | B103: Ngâm nước thử bể | C103: m3 | D103: 211.896 | F103: =BBNTHT!J143 -> 0 | G103: =F103+E103 -> 0 | H103: 19050 | I103: =ROUND(D103*H103,0) -> 4036619 | K103: =ROUND(F103*H103,0) -> 0 | L103: =J103+K103 -> 0
A104: 3 | B104: KẾT CẤU - PHẦN THÂN | F104: =BBNTHT!J144 -> 0 | G104: =F104+E104 -> 0 | K104: =ROUND(F104*H104,0) -> 0 | L104: =J104+K104 -> 0
A105: 3.1 | B105: Đổ bê tông bằng máy, đổ bằng cần cẩu, bê tông tường, chiều dày ≤45cm, chiều cao ≤100m, đá 1x2, mác 400 | C105: m3 | D105: 230.4 | F105: =BBNTHT!J145 -> 0 | G105: =F105+E105 -> 0 | H105: 3869643 | I105: =ROUND(D105*H105,0) -> 891565747 | K105: =ROUND(F105*H105,0) -> 0 | L105: =J105+K105 -> 0
A106: 3.2 | B106: Đổ bê tông bằng máy, đổ bằng cần cẩu, bê tông tường, chiều dày ≤45cm, chiều cao ≤100m, đá 1x2, mác 400 | C106: m3 | D106: 648.78 | F106: =BBNTHT!J146 -> 0 | G106: =F106+E106 -> 0 | H106: 3041481 | I106: =ROUND(D106*H106,0) -> 1973252043 | K106: =ROUND(F106*H106,0) -> 0 | L106: =J106+K106 -> 0
A107: 3.3 | B107: Ván khuôn bằng ván ép phủ phim có khung xương, cột chống bằng hệ giáo ống. Ván khuôn tường, chiều cao ≤100m | C107: 100m2 | D107: 51.759 | F107: =BBNTHT!J147 -> 0 | G107: =F107+E107 -> 0 | H107: 12583749 | I107: =ROUND(D107*H107,0) -> 651322264 | K107: =ROUND(F107*H107,0) -> 0 | L107: =J107+K107 -> 0
A108: 3.4 | B108: Công tác gia công lắp dựng cốt thép. Cốt thép tường, D≤10mm, chiều cao ≤100m | C108: tấn | D108: 33.622 | F108: =BBNTHT!J148 -> 20.84564 | G108: =F108+E108 -> 20.84564 | H108: 25563194 | I108: =ROUND(D108*H108,0) -> 859485709 | K108: =ROUND(F108*H108,0) -> 532881139 | L108: =J108+K108 -> 532881139
A109: 3.5 | B109: Công tác gia công lắp dựng cốt thép. Cốt thép tường, D≤18mm, chiều cao ≤100m | C109: tấn | D109: 121.305 | F109: =BBNTHT!J149 -> 75.2091 | G109: =F109+E109 -> 75.2091 | H109: 26337656 | I109: =ROUND(D109*H109,0) -> 3194889361 | K109: =ROUND(F109*H109,0) -> 1980831404 | L109: =J109+K109 -> 1980831404
A110: 3.6 | B110: Công tác gia công lắp dựng cốt thép. Cốt thép tường, D>18mm, chiều cao ≤100m | C110: tấn | D110: 38.942 | F110: =BBNTHT!J150 -> 24.14404 | G110: =F110+E110 -> 24.14404 | H110: 25555078 | I110: =ROUND(D110*H110,0) -> 995165847 | K110: =ROUND(F110*H110,0) -> 617002825 | L110: =J110+K110 -> 617002825
A111: 3.7 | B111: Đổ bê tông bằng máy, đổ bằng cần cẩu, bê tông vách thang máy, chiều dày ≤45cm, chiều cao ≤100m, đá 1x2, mác 500 | C111: m3 | D111: 227.604 | F111: =BBNTHT!J151 -> 0 | G111: =F111+E111 -> 0 | H111: 3215438 | I111: =ROUND(D111*H111,0) -> 731846551 | K111: =ROUND(F111*H111,0) -> 0 | L111: =J111+K111 -> 0
A112: 3.8 | B112: Đổ bê tông bằng máy, đổ bằng cần cẩu, bê tông vách thang máy, chiều dày ≤45cm, chiều cao ≤100m, đá 1x2, mác 400 | C112: m3 | D112: 370.689 | F112: =BBNTHT!J152 -> 0 | G112: =F112+E112 -> 0 | H112: 3041481 | I112: =ROUND(D112*H112,0) -> 1127443550 | K112: =ROUND(F112*H112,0) -> 0 | L112: =J112+K112 -> 0
A113: 3.9 | B113: Ván khuôn bằng ván ép phủ phim có khung xương, cột chống bằng hệ giáo ống. Ván khuôn vách thang máy, chiều cao ≤100m | C113: 100m2 | D113: 38.263 | F113: =BBNTHT!J153 -> 0 | G113: =F113+E113 -> 0 | H113: 12583749 | I113: =ROUND(D113*H113,0) -> 481491988 | K113: =ROUND(F113*H113,0) -> 0 | L113: =J113+K113 -> 0
A114: 3.10 | B114: Công tác gia công lắp dựng cốt thép. Cốt thép vách thang máy, D≤10mm, chiều cao ≤100m | C114: tấn | D114: 20.697 | F114: =BBNTHT!J154 -> 12.83214 | G114: =F114+E114 -> 12.83214 | H114: 25563194 | I114: =ROUND(D114*H114,0) -> 529081426 | K114: =ROUND(F114*H114,0) -> 328030484 | L114: =J114+K114 -> 328030484
A115: 3.11 | B115: Công tác gia công lắp dựng cốt thép. Cốt thép vách thang máy, D≤18mm, chiều cao ≤100m | C115: tấn | D115: 70.976 | F115: =BBNTHT!J155 -> 44.00512 | G115: =F115+E115 -> 44.00512 | H115: 26337656 | I115: =ROUND(D115*H115,0) -> 1869341472 | K115: =ROUND(F115*H115,0) -> 1158991713 | L115: =J115+K115 -> 1158991713
A116: 3.12 | B116: Công tác gia công lắp dựng cốt thép. Cốt thép vách thang máy, D>18mm, chiều cao ≤100m | C116: tấn | D116: 6.04 | F116: =BBNTHT!J156 -> 3.7448 | G116: =F116+E116 -> 3.7448 | H116: 25555078 | I116: =ROUND(D116*H116,0) -> 154352671 | K116: =ROUND(F116*H116,0) -> 95698656 | L116: =J116+K116 -> 95698656
... A154: 3.50 | B154: Công tác gia công lắp dựng cốt thép. Cốt thép cột, trụ, D≤10mm, chiều cao ≤100m | C154: tấn | D154: 1.919 | F154: =BBNTHT!J194 -> 0.72922 | G154: =F154+E154 -> 0.72922 | H154: 25939010 | I154: =ROUND(D154*H154,0) -> 49776960 | K154: =ROUND(F154*H154,0) -> 18915245 | L154: =J154+K154 -> 18915245
A155: 4 | B155: HOÀN THIỆN KIẾN TRÚC | F155: =BBNTHT!J195 -> 0 | G155: =F155+E155 -> 0 | K155: =ROUND(F155*H155,0) -> 0 | L155: =J155+K155 -> 0
A156: 4.1 | B156: Xây không nung đặc 5x9x19cm, xây các bộ phận kết cấu phức tạp khác, chiều cao ≤100m, vữa XM mác 75 | C156: m3 | D156: 54.519 | F156: =BBNTHT!J196 -> 0 | G156: =F156+E156 -> 0 | H156: 3693206 | I156: =ROUND(D156*H156,0) -> 201349898 | K156: =ROUND(F156*H156,0) -> 0 | L156: =J156+K156 -> 0
A157: 4.2 | B157: Lát đá granit tự nhiên màu trắng bậc tam cấp, vữa XM mác 75 | C157: m2 | D157: 156.037 | F157: =BBNTHT!J197 -> 0 | G157: =F157+E157 -> 0 | H157: 3087605 | I157: =ROUND(D157*H157,0) -> 481780621 | K157: =ROUND(F157*H157,0) -> 0 | L157: =J157+K157 -> 0
A158: 4.3 | B158: Lát granito đúc sẵn bậc cầu thang, vữa XM mác 75 | C158: m2 | D158: 844.669 | F158: =BBNTHT!J198 -> 0 | G158: =F158+E158 -> 0 | H158: 2162469 | I158: =ROUND(D158*H158,0) -> 1826570528 | K158: =ROUND(F158*H158,0) -> 0 | L158: =J158+K158 -> 0
A159: 4.4 | B159: CC lan can thép []25x50x1.8 (chi tiết theo thiết kế) | C159: m2 | D159: 282.289 | F159: =BBNTHT!J199 -> 0 | G159: =F159+E159 -> 0 | H159: 1523967 | I159: =ROUND(D159*H159,0) -> 430199120 | K159: =ROUND(F159*H159,0) -> 0 | L159: =J159+K159 -> 0
A160: 4.5 | B160: Lắp dựng lan can sắt | C160: m2 | D160: 282.289 | F160: =BBNTHT!J200 -> 0 | G160: =F160+E160 -> 0 | H160: 180503 | I160: =ROUND(D160*H160,0) -> 50954011 | K160: =ROUND(F160*H160,0) -> 0 | L160: =J160+K160 -> 0
A161: 4.6 | B161: CC lan can inox D60 (chi tiết theo thiết kế) | C161: m2 | D161: 8.864 | F161: =BBNTHT!J201 -> 0 | G161: =F161+E161 -> 0 | H161: 2158953 | I161: =ROUND(D161*H161,0) -> 19136959 | K161: =ROUND(F161*H161,0) -> 0 | L161: =J161+K161 -> 0
A162: 4.7 | B162: Lắp dựng lan can sắt | C162: m2 | D162: 8.864 | F162: =BBNTHT!J202 -> 0 | G162: =F162+E162 -> 0 | H162: 180841 | I162: =ROUND(D162*H162,0) -> 1602975 | K162: =ROUND(F162*H162,0) -> 0 | L162: =J162+K162 -> 0
A163: 4.8 | B163: Sơn sắt thép bằng sơn các loại, 1 nước lót, 2 nước phủ | C163: m2 | D163: 572.342 | F163: =BBNTHT!J203 -> 0 | G163: =F163+E163 -> 0 | H163: 177682 | I163: =ROUND(D163*H163,0) -> 101694871 | K163: =ROUND(F163*H163,0) -> 0 | L163: =J163+K163 -> 0
A164: 4.9 | B164: CC lan can kính cường lực dày 12mm tay vịn D60 cao 1.05m, khung thép []50x50 | C164: m2 | D164: 36.931 | F164: =BBNTHT!J204 -> 0 | G164: =F164+E164 -> 0 | H164: 2857437 | I164: =ROUND(D164*H164,0) -> 105528006 | K164: =ROUND(F164*H164,0) -> 0 | L164: =J164+K164 -> 0
A165: 4.10 | B165: CC lan can kính cường lực dày 12mm tay vịn D60 cao 1.4m, khung thép []50x50 | C165: m2 | D165: 1255.33 | F165: =BBNTHT!J205 -> 0 | G165: =F165+E165 -> 0 | H165: 2857437 | I165: =ROUND(D165*H165,0) -> 3587026389 | K165: =ROUND(F165*H165,0) -> 0 | L165: =J165+K165 -> 0
A166: 4.11 | B166: Lắp dựng lan can kính | C166: m2 | D166: 1292.261 | F166: =BBNTHT!J206 -> 0 | G166: =F166+E166 -> 0 | H166: 168782 | I166: =ROUND(D166*H166,0) -> 218110396 | K166: =ROUND(F166*H166,0) -> 0 | L166: =J166+K166 -> 0
A167: 4.12 | B167: Mái sảnh kính cường lực dày 12mm | C167: m2 | D167: 184.415 | F167: =BBNTHT!J207 -> 0 | G167: =F167+E167 -> 0 | H167: 1523967 | I167: =ROUND(D167*H167,0) -> 281042374 | K167: =ROUND(F167*H167,0) -> 0 | L167: =J167+K167 -> 0
... A254: 4.99 | B254: Phòng mối nền công trình xây mới. | C254: m2 | D254: 1247.15 | F254: =BBNTHT!J294 -> 0 | G254: =F254+E254 -> 0 | H254: 230235 | I254: =ROUND(D254*H254,0) -> 287137580 | K254: =ROUND(F254*H254,0) -> 0 | L254: =J254+K254 -> 0
A255: 5 | B255: HỆ THỐNG ĐIỆN | F255: =BBNTHT!J295 -> 0 | G255: =F255+E255 -> 0 | K255: =ROUND(F255*H255,0) -> 0 | L255: =J255+K255 -> 0
A256: 5.1 | B256: Tủ điện LV1.1 | F256: =BBNTHT!J296 -> 0 | G256: =F256+E256 -> 0 | K256: =ROUND(F256*H256,0) -> 0 | L256: =J256+K256 -> 0
A257: 5.1.1 | B257: ACB 3P 1600A 42kA | C257: cái | D257: 1 | F257: =BBNTHT!J297 -> 0 | G257: =F257+E257 -> 0 | H257: 66354638 | I257: =ROUND(D257*H257,0) -> 66354638 | K257: =ROUND(F257*H257,0) -> 0 | L257: =J257+K257 -> 0
A258: 5.1.2 | B258: Biến dòng 1600A/5A | C258: bộ | D258: 6 | F258: =BBNTHT!J298 -> 0 | G258: =F258+E258 -> 0 | H258: 1452644 | I258: =ROUND(D258*H258,0) -> 8715864 | K258: =ROUND(F258*H258,0) -> 0 | L258: =J258+K258 -> 0
A259: 5.1.3 | B259: Đèn báo pha | C259: bộ | D259: 3 | F259: =BBNTHT!J299 -> 0 | G259: =F259+E259 -> 0 | H259: 396005 | I259: =ROUND(D259*H259,0) -> 1188015 | K259: =ROUND(F259*H259,0) -> 0 | L259: =J259+K259 -> 0
A260: 5.1.4 | B260: Cầu chì 220V-2A | C260: bộ | D260: 6 | F260: =BBNTHT!J300 -> 0 | G260: =F260+E260 -> 0 | H260: 83756 | I260: =ROUND(D260*H260,0) -> 502536 | K260: =ROUND(F260*H260,0) -> 0 | L260: =J260+K260 -> 0
A261: 5.1.5 | B261: Công tơ điện đa năng | C261: cái | D261: 1 | F261: =BBNTHT!J301 -> 0 | G261: =F261+E261 -> 0 | H261: 7204683 | I261: =ROUND(D261*H261,0) -> 7204683 | K261: =ROUND(F261*H261,0) -> 0 | L261: =J261+K261 -> 0
A262: 5.1.6 | B262: Công tắc chuyển mạch vôn kế | C262: cái | D262: 1 | F262: =BBNTHT!J302 -> 0 | G262: =F262+E262 -> 0 | H262: 50113 | I262: =ROUND(D262*H262,0) -> 50113 | K262: =ROUND(F262*H262,0) -> 0 | L262: =J262+K262 -> 0
A263: 5.1.7 | B263: Vôn kế | C263: cái | D263: 1 | F263: =BBNTHT!J303 -> 0 | G263: =F263+E263 -> 0 | H263: 397618 | I263: =ROUND(D263*H263,0) -> 397618 | K263: =ROUND(F263*H263,0) -> 0 | L263: =J263+K263 -> 0
A264: 5.1.8 | B264: Ampe kế 0-1600A | C264: cái | D264: 3 | F264: =BBNTHT!J304 -> 0 | G264: =F264+E264 -> 0 | H264: 614082 | I264: =ROUND(D264*H264,0) -> 1842246 | K264: =ROUND(F264*H264,0) -> 0 | L264: =J264+K264 -> 0
A265: 5.1.9 | B265: Hệ thống thanh cái, cáp nối | C265: Bộ | D265: 1 | F265: =BBNTHT!J305 -> 0 | G265: =F265+E265 -> 0 | H265: 634986 | I265: =ROUND(D265*H265,0) -> 634986 | K265: =ROUND(F265*H265,0) -> 0 | L265: =J265+K265 -> 0
A266: 5.1.10 | B266: Vỏ tủ trong nhà, 2 lớp cánh, tôn dày 1.5mm, kt C2200xR800xS800mm | C266: tủ | D266: 1 | F266: =BBNTHT!J306 -> 0 | G266: =F266+E266 -> 0 | H266: 5935608 | I266: =ROUND(D266*H266,0) -> 5935608 | K266: =ROUND(F266*H266,0) -> 0 | L266: =J266+K266 -> 0
A267: 5.2 | B267: Tủ điện LV1.2 | F267: =BBNTHT!J307 -> 0 | G267: =F267+E267 -> 0
A268: 5.2.1 | B268: ACB 3P 1250A 42kA | C268: cái | D268: 1 | F268: =BBNTHT!J308 -> 0 | G268: =F268+E268 -> 0 | H268: 60738822 | I268: =ROUND(D268*H268,0) -> 60738822 | K268: =ROUND(F268*H268,0) -> 0 | L268: =J268+K268 -> 0
A269: 5.2.2 | B269: MCCB 3P 125A 36kA | C269: cái | D269: 1 | F269: =BBNTHT!J309 -> 0 | G269: =F269+E269 -> 0 | H269: 3748221 | I269: =ROUND(D269*H269,0) -> 3748221 | K269: =ROUND(F269*H269,0) -> 0 | L269: =J269+K269 -> 0
A270: 5.2.3 | B270: MCCB 3P 100A 36kA | C270: bộ | D270: 3 | F270: =BBNTHT!J310 -> 0 | G270: =F270+E270 -> 0 | H270: 3720561 | I270: =ROUND(D270*H270,0) -> 11161683 | K270: =ROUND(F270*H270,0) -> 0 | L270: =J270+K270 -> 0
A271: 5.2.4 | B271: MCCB 3P 50A 36kA | C271: cái | D271: 2 | F271: =BBNTHT!J311 -> 0 | G271: =F271+E271 -> 0 | H271: 2585790 | I271: =ROUND(D271*H271,0) -> 5171580 | K271: =ROUND(F271*H271,0) -> 0 | L271: =J271+K271 -> 0
A272: 5.2.5 | B272: MCCB 3P 25A 36kA | C272: cái | D272: 3 | F272: =BBNTHT!J312 -> 0 | G272: =F272+E272 -> 0 | H272: 2585790 | I272: =ROUND(D272*H272,0) -> 7757370 | K272: =ROUND(F272*H272,0) -> 0 | L272: =J272+K272 -> 0
A273: 5.2.6 | B273: Hệ thống thanh cái, cáp nối | C273: bộ | D273: 1 | F273: =BBNTHT!J313 -> 0 | G273: =F273+E273 -> 0 | H273: 634986 | I273: =ROUND(D273*H273,0) -> 634986 | K273: =ROUND(F273*H273,0) -> 0 | L273: =J273+K273 -> 0
A274: 5.2.7 | B274: Vỏ tủ trong nhà, 2 lớp cánh, tôn dày 1.5mm, kt C2200xR800xS800mm | C274: tủ | D274: 1 | F274: =BBNTHT!J314 -> 0 | G274: =F274+E274 -> 0 | H274: 5935608 | I274: =ROUND(D274*H274,0) -> 5935608 | K274: =ROUND(F274*H274,0) -> 0 | L274: =J274+K274 -> 0
A275: 5.3 | B275: Tủ điện LV1.3 | F275: =BBNTHT!J315 -> 0 | G275: =F275+E275 -> 0 | K275: =ROUND(F275*H275,0) -> 0 | L275: =J275+K275 -> 0
A276: 5.3.1 | B276: MCCB 3P 630A 42kA | C276: cái | D276: 1 | F276: =BBNTHT!J316 -> 0 | G276: =F276+E276 -> 0 | H276: 14574262 | I276: =ROUND(D276*H276,0) -> 14574262 | K276: =ROUND(F276*H276,0) -> 0 | L276: =J276+K276 -> 0
A277: 5.3.2 | B277: MCCB 3P 300A 36kA | C277: cái | D277: 2 | F277: =BBNTHT!J317 -> 0 | G277: =F277+E277 -> 0 | H277: 9239236 | I277: =ROUND(D277*H277,0) -> 18478472 | K277: =ROUND(F277*H277,0) -> 0 | L277: =J277+K277 -> 0
A278: 5.3.3 | B278: MCCB 3P 250A 36kA | C278: cái | D278: 1 | F278: =BBNTHT!J318 -> 0 | G278: =F278+E278 -> 0 | H278: 3942500 | I278: =ROUND(D278*H278,0) -> 3942500 | K278: =ROUND(F278*H278,0) -> 0 | L278: =J278+K278 -> 0
A279: 5.3.4 | B279: MCCB 3P 160A 36kA | C279: cái | D279: 1 | F279: =BBNTHT!J319 -> 0 | G279: =F279+E279 -> 0 | H279: 6048623 | I279: =ROUND(D279*H279,0) -> 6048623 | K279: =ROUND(F279*H279,0) -> 0 | L279: =J279+K279 -> 0
A280: 5.3.5 | B280: MCCB 3P 80A 36kA | C280: cái | D280: 1 | F280: =BBNTHT!J320 -> 0 | G280: =F280+E280 -> 0 | H280: 3720561 | I280: =ROUND(D280*H280,0) -> 3720561 | K280: =ROUND(F280*H280,0) -> 0 | L280: =J280+K280 -> 0
A281: 5.3.6 | B281: MCCB 3P 25A 36kA | C281: cái | D281: 1 | F281: =BBNTHT!J321 -> 0 | G281: =F281+E281 -> 0 | H281: 2585790 | I281: =ROUND(D281*H281,0) -> 2585790 | K281: =ROUND(F281*H281,0) -> 0 | L281: =J281+K281 -> 0
A282: 5.3.7 | B282: Biến dòng 630A/5A | C282: bộ | D282: 7 | F282: =BBNTHT!J322 -> 0 | G282: =F282+E282 -> 0 | H282: 1042190 | I282: =ROUND(D282*H282,0) -> 7295330 | K282: =ROUND(F282*H282,0) -> 0 | L282: =J282+K282 -> 0
A283: 5.3.8 | B283: Đèn báo pha | C283: bộ | D283: 3 | F283: =BBNTHT!J323 -> 0 | G283: =F283+E283 -> 0 | H283: 396005 | I283: =ROUND(D283*H283,0) -> 1188015 | K283: =ROUND(F283*H283,0) -> 0 | L283: =J283+K283 -> 0
...

Sheet bảng diễn giải
A5: STT | B5: Diễn giải khối lượng | C5: Đơn vị | D5: Số lượng | E5: Kích thước | H5: Hệ số | I5: Khối lượng
E6: Dài | F6: Rộng | G6: Cao | I6: Chi tiết | J6: Theo HĐ | K6: Thực hiện kỳ này | L6: Lũy kế đến hết kỳ trước | M6: Thanh toán kỳ này | N6: Lũy kế đến hết kỳ này
A7: 1 | B7: 2 | C7: 3 | D7: 4 | E7: 5 | F7: 6 | G7: 7 | H7: 8 | I7: 9 | J7: 10 | K7: 11 | L7: 12 | M7: 13 | N7: 14
B8: HẠNG MỤC: PHẦN CỌC
A9: 1 | B9: Cọc PHC D600 Class A | C9: m | I9: =ROUND(SUM(I10:I11),3) -> 6556.9 | J9: =PL03a!#REF! -> #REF! | K9: =I9 -> 6556.9 | M9: =K9 -> 6556.9 | N9: =L9+M9 -> 6556.9
B10: Cọc thí nghiệm | D10: 2 | E10: 32.3 | I10: =ROUND(PRODUCT(D10:E10),3) -> 64.6
B11: Cọc đại trà loại 1 | D11: 201 | E11: =32+0.3 -> 32.3 | I11: =ROUND(PRODUCT(D11:E11),3) -> 6492.3
A12: 2 | B12: Mũi cọc | C12: cái | I12: =ROUND(SUM(I13:I14),3) -> 203 | J12: =PL03a!#REF! -> #REF! | K12: =I12 -> 203 | M12: =K12 -> 203 | N12: =L12+M12 -> 203
B13: Cọc thí nghiệm | D13: 2 | I13: =ROUND(PRODUCT(D13:E13),3) -> 2
B14: Cọc đại trà loại 1 | D14: 201 | I14: =ROUND(PRODUCT(D14:E14),3) -> 201
A15: 3 | B15: Khoan dẫn phục vụ đóng, ép cọc bằng máy khoan xoay, đường kính 400mm | C15: m | I15: =ROUND(SUM(I16:I18),3) -> 4466 | J15: =PL03a!#REF! -> #REF! | K15: =I15 -> 4466 | M15: =J15 -> #REF! | N15: =L15+M15 -> #REF!
B16: Phần đất cát:
B17: Cọc thí nghiệm | D17: 2 | E17: 22 | I17: =ROUND(PRODUCT(D17:E17),3) -> 44
B18: Cọc đại trà loại 1 | D18: 201 | E18: 22 | I18: =ROUND(PRODUCT(D18:E18),3) -> 4422
A19: 4 | B19: Ép cọc ống bê tông cốt thép dự ứng lực bằng máy ép Robot thủy lực tự hành 860T, đất cấp I, đường kính cọc 600mm | C19: 100m | I19: =ROUND(SUM(I20:I23),3) -> 57.631 | J19: =PL03a!#REF! -> #REF! | K19: =I19 -> 57.631 | M19: =K19 -> 57.631 | N19: =L19+M19 -> 57.631
B20: Cọc thí nghiệm | D20: 2 | E20: 32 | H20: 0.01 | I20: =ROUND(PRODUCT(D20:H20),3) -> 0.64
B21: Cọc đại trà loại 1, dưới đài cọc cao 1.5m | D21: 11 | E21: 28.95 | H21: 0.01 | I21: =ROUND(PRODUCT(D21:H21),3) -> 3.185
B22: Cọc đại trà loại 1, dưới đài cọc cao 2.0m | D22: 165 | E22: 28.45 | H22: 0.01 | I22: =ROUND(PRODUCT(D22:H22),3) -> 46.943
B23: Cọc đại trà loại 1, dưới đài cọc cao 3.0m | D23: 25 | E23: 27.45 | H23: 0.01 | I23: =ROUND(PRODUCT(D23:H23),3) -> 6.863
A24: 5 | B24: Ép cọc ống bê tông cốt thép dự ứng lực bằng máy ép Robot thủy lực tự hành 860T, đất cấp I, đường kính cọc 600mm, đoạn cọc không ngập đất (NC, MTC x 0.75) | C24: 100m | I24: =ROUND(SUM(I25:I25),3) -> 0.006 | J24: =PL03a!#REF! -> #REF! | K24: =I24 -> 0.006 | M24: =K24 -> 0.006 | N24: =L24+M24 -> 0.006
B25: Cọc thí nghiệm | D25: 2 | E25: 0.3 | H25: 0.01 | I25: =ROUND(PRODUCT(D25:H25),3) -> 0.006 | K25: =I25 -> 0.006 | M25: =K25 -> 0.006 | N25: =L25+M25 -> 0.006
A26: 6 | B26: Ép cọc ống bê tông cốt thép dự ứng lực bằng máy ép Robot thủy lực tự hành 860T, đất cấp I, đường kính cọc 600mm, ép âm sử dụng cọc dẫn (NC, MTC x 1.05) | C26: 100m | I26: =ROUND(SUM(I27:I29),3) -> 6.729 | J26: =PL03a!#REF! -> #REF! | K26: =I26 -> 6.729 | M26: =K26 -> 6.729 | N26: =L26+M26 -> 6.729
B27: Cọc đại trà loại 1, dưới đài cọc cao 1.5m | D27: 11 | E27: 2.75 | H27: 0.01 | I27: =ROUND(PRODUCT(D27:H27),3) -> 0.303
B28: Cọc đại trà loại 1, dưới đài cọc cao 2.0m | D28: 165 | E28: 3.25 | H28: 0.01 | I28: =ROUND(PRODUCT(D28:H28),3) -> 5.363
B29: Cọc đại trà loại 1, dưới đài cọc cao 3.0m | D29: 25 | E29: 4.25 | H29: 0.01 | I29: =ROUND(PRODUCT(D29:H29),3) -> 1.063
A30: 7 | B30: Nối cọc ống bê tông cốt thép, đường kính cọc <= 600mm | C30: mối nối | E30: 203 | I30: =ROUND(PRODUCT(D30:E30),3) -> 203 | J30: =PL03a!#REF! -> #REF! | K30: =I30 -> 203 | M30: =K30 -> 203 | N30: =L30+M30 -> 203
A31: 8 | B31: Cắt đầu cọc (VD mã hiệu) | C31: mối | I31: =ROUND(SUM(I32:I33),3) -> 205 | J31: 203 | K31: =I31 -> 205 | M31: =J31 -> 203 | N31: =L31+M31 -> 203
B32: Cọc thí nghiệm | D32: 4 | I32: =ROUND(PRODUCT(D32:E32),3) -> 4
B33: Cọc đại trà loại 1 | D33: 201 | I33: =ROUND(PRODUCT(D33:E33),3) -> 201
A34: 9 | B34: Vận chuyển đất bằng ôtô tự đổ 7 tấn trong phạm vi <= 1000m, đất cấp III | C34: 100m3 | I34: =I35 -> 0.3442068 | J34: =PL03a!#REF! -> #REF! | K34: =I34 -> 0.3442068 | M34: =K34 -> 0.3442068 | N34: =L34+M34 -> 0.3442068
B35: BT đầu cọc: 203*3,14*0,3*0,3*0,6*0,01 = 0,344 | I35: =203*3.14*0.3*0.3*0.6*0.01 -> 0.3442068
A36: 10 | B36: Vận chuyển đất bằng ô tô tự đổ 7T 1km tiếp theo ngoài phạm vi 5km, đất cấp III | C36: 100m3 | I36: =ROUND(SUM(I37:I37),3) -> 0.344 | J36: 3.44 | K36: =I36 -> 0.344 | M36: =K36 -> 0.344 | N36: =L36+M36 -> 0.344
B37: VC xa 5km, MTC x 4 | E37: =L34 -> 0 | I37: =I35 -> 0.3442068
A38: 11 | B38: Gia công cấu kiện thép đặt sẵn trong bê tông, khối lượng một cấu kiện <= 50 kg | C38: tấn | I38: =ROUND(SUM(I39:I39),3) -> 9.354 | J38: =PL03a!#REF! -> #REF! | K38: =I38 -> 9.354 | M38: =K38 -> 9.354 | N38: =L38+M38 -> 9.354
B39: Thép liên kết cọc với đài | D39: 203 | E39: =34.3+3.39+7.13+1.26 -> 46.08 | H39: 0.001 | I39: =ROUND(PRODUCT(D39:H39),3) -> 9.354
A40: 12 | B40: Lắp đặt cấu kiện thép đặt sẵn trong bê tông, khối lượng một cấu kiện <= 50 kg | C40: tấn | E40: =J38 -> #REF! | I40: =ROUND(PRODUCT(D40:E40),3) -> #REF! | J40: =PL03a!#REF! -> #REF! | K40: =I40 -> #REF! | M40: =K40 -> #REF! | N40: =L40+M40 -> #REF!
A41: 13 | B41: Đổ bê tông thủ công bằng máy trộn, bê tông móng, chiều rộng <= 250 cm, đá 1x2, mác 300 | C41: m3 | I41: =ROUND(SUM(I42:I42),3) -> 53.409 | J41: =PL03a!#REF! -> #REF! | K41: =I41 -> 53.409 | M41: =K41 -> 53.409 | N41: =L41+M41 -> 53.409
B42: BT chèn cọc ( tính theo đk trong của cọc) | D42: 203 | E42: 3.14 | F42: =0.21*0.21 -> 0.0441 | G42: 1.9 | I42: =ROUND(PRODUCT(D42:H42),3) -> 53.409
B43: HẠNG MỤC: PHẦN DƯỚI CỐT 0.0M
A44: 1 | B44: Đào móng công trình, chiều rộng móng ≤6m, bằng máy đào 1,25m3, đất cấp II | C44: 100m3 | I44: =SUM(I45:I141) -> 48.676 | J44: =PL03a!#REF! -> #REF! | K44: =I44 -> 48.676 | M44: =K44 -> 48.676 | N44: =L44+M44 -> 48.676
B45: Móng ( theo chu vi đóng cừ)
B46: (A-D)(1-4) | E46: 25.25 | F46: 27.2 | G46: 2.25 | H46: 0.01 | I46: =ROUND(PRODUCT(D46:H46),3) -> 15.453
B47: (A-D)(4-8) | E47: 30.8 | F47: 30.4 | G47: 2.25 | H47: 0.01 | I47: =ROUND(PRODUCT(D47:H47),3) -> 21.067
B48: Đài cọc:
B49: M1 | D49: 5 | E49: 1.3 | F49: 1.3 | G49: 1.1 | H49: 0.01 | I49: =ROUND(PRODUCT(D49:H49),3) -> 0.093
B50: M2 | D50: 3 | E50: 1.3 | F50: 3.1 | G50: 1.1 | H50: 0.01 | I50: =ROUND(PRODUCT(D50:H50),3) -> 0.133
B51: M4 | D51: 2 | E51: 3.1 | F51: 3.1 | G51: 1.6 | H51: 0.01 | I51: =ROUND(PRODUCT(D51:H51),3) -> 0.308
B52: M5 | E52: 3.1 | F52: 4.5 | G52: 1.6 | H52: 0.01 | I52: =ROUND(PRODUCT(D52:H52),3) -> 0.223
B53: M6 | E53: 3.1 | F53: 4.9 | G53: 1.6 | H53: 0.01 | I53: =ROUND(PRODUCT(D53:H53),3) -> 0.243
B54: M6A | E54: 4.9 | F54: 3.1 | G54: 1.6 | H54: 0.01 | I54: =ROUND(PRODUCT(D54:H54),3) -> 0.243
B55: M8 | D55: 3 | E55: 3.1 | F55: 6.7 | G55: 1.6 | H55: 0.01 | I55: =ROUND(PRODUCT(D55:H55),3) -> 0.997
B56: M8A | E56: 4.5 | F56: 4.9 | G56: 1.6 | H56: 0.01 | I56: =ROUND(PRODUCT(D56:H56),3) -> 0.353
B57: M8A1 | E57: 4.5 | F57: 4.9 | G57: 1.6 | H57: 0.01 | I57: =ROUND(PRODUCT(D57:H57),3) -> 0.353
B58: M9 | E58: 4.9 | F58: 4.9 | G58: 1.6 | H58: 0.01 | I58: =ROUND(PRODUCT(D58:H58),3) -> 0.384
B59: M9A | E59: 4.9 | F59: 4.9 | G59: 1.6 | H59: 0.01 | I59: =ROUND(PRODUCT(D59:H59),3) -> 0.384
B60: M10 | E60: 4.5 | F60: 6.7 | G60: 1.6 | H60: 0.01 | I60: =ROUND(PRODUCT(D60:H60),3) -> 0.482
B61: M10A | E61: 3.1 | F61: 8.5 | G61: 1.6 | H61: 0.01 | I61: =ROUND(PRODUCT(D61:H61),3) -> 0.422
B62: M11 | E62: 4.5 | F62: 6.7 | G62: 1.6 | H62: 0.01 | I62: =ROUND(PRODUCT(D62:H62),3) -> 0.482
B63: M13 | E63: 4.5 | F63: 8.5 | G63: 1.6 | H63: 0.01 | I63: =ROUND(PRODUCT(D63:H63),3) -> 0.612
B64: M19 | D64: 2 | E64: 3.1 | F64: 3.2 | G64: 1.6 | H64: 0.01 | I64: =ROUND(PRODUCT(D64:H64),3) -> 0.317
E65: 4.9 | F65: 6.9 | G65: 1.6 | H65: 0.01 | I65: =ROUND(PRODUCT(D65:H65),3) -> 0.541
B66: M21 | E66: 3.1 | F66: 3.3 | G66: 1.6 | H66: 0.01 | I66: =ROUND(PRODUCT(D66:H66),3) -> 0.164
E67: 3.1 | F67: 1.6 | G67: 1.6 | H67: 0.01 | I67: =ROUND(PRODUCT(D67:H67),3) -> 0.079
E68: 4.9 | F68: 8.7 | G68: 1.6 | H68: 0.01 | I68: =ROUND(PRODUCT(D68:H68),3) -> 0.682
B69: M25 | E69: 4.9 | F69: 1.9 | G69: 2.6 | H69: 0.01 | I69: =ROUND(PRODUCT(D69:H69),3) -> 0.242
E70: 4.9 | F70: 3.6 | G70: 2.6 | H70: 0.01 | I70: =ROUND(PRODUCT(D70:H70),3) -> 0.459
E71: 6.7 | F71: 6.7 | G71: 2.6 | H71: 0.01 | I71: =ROUND(PRODUCT(D71:H71),3) -> 1.167
B72: Dầm móng:
B73: DM-1: 54,2-(1,65+3,1+3,1+4,9+3,1+4,5+3,1+0,85) = 29,9 | E73: 29.9 | F73: 0.6 | G73: 0.4 | H73: 0.01 | I73: =ROUND(PRODUCT(D73:H73),3) -> 0.072
B74: DM-2: 23,4-(1,65+4,5+3,1+5,55) = 8,6 | E74: 8.6 | F74: 0.6 | G74: 0.4 | H74: 0.01 | I74: =ROUND(PRODUCT(D74:H74),3) -> 0.021
B75: DM-3:9,6-(2,25+2,15) = 5,2 | E75: 5.2 | F75: 0.6 | G75: 0.4 | H75: 0.01 | I75: =ROUND(PRODUCT(D75:H75),3) -> 0.012
B76: DM-4: 30,8-(1,25+4,9+4,5+3,1+0,95) = 16,1 | E76: 16.1 | F76: 0.6 | G76: 0.4 | H76: 0.01 | I76: =ROUND(PRODUCT(D76:H76),3) -> 0.039
B77: DM-5:15,6-(1,65+4,5+2,25) = 7,2 | E77: 7.2 | F77: 0.6 | G77: 0.4 | H77: 0.01 | I77: =ROUND(PRODUCT(D77:H77),3) -> 0.017
B78: DM-5A:30,8-(2,25+6,7+4,9+3,1+0,95) = 12,9 | E78: 12.9 | F78: 0.6 | G78: 0.4 | H78: 0.01 | I78: =ROUND(PRODUCT(D78:H78),3) -> 0.031
B79: DM-6:9,6-(2,45+2,95) = 4,2 | E79: 4.2 | F79: 0.6 | G79: 0.4 | H79: 0.01 | I79: =ROUND(PRODUCT(D79:H79),3) -> 0.01
B80: DM-7:38,1-(0,75+2*1,3+4,9+3,1+2,45) = 24,3 | E80: 24.3 | F80: 0.6 | G80: 0.4 | H80: 0.01 | I80: =ROUND(PRODUCT(D80:H80),3) -> 0.058
B81: DM7A:6,9-(2,45+2,95) = 1,5 | E81: 1.5 | F81: 0.5 | G81: 1.4 | H81: 0.01 | I81: =ROUND(PRODUCT(D81:H81),3) -> 0.011
B82: DM7B:6,5-(1,95+0,85) = 3,7 | E82: 3.7 | F82: 0.6 | G82: 0.4 | H82: 0.01 | I82: =ROUND(PRODUCT(D82:H82),3) -> 0.009
B83: DM-8:6,9-(1,55+2,05) = 3,3 | E83: 3.3 | F83: 0.6 | G83: 0.4 | H83: 0.01 | I83: =ROUND(PRODUCT(D83:H83),3) -> 0.008
B84: DM8A:(2,1-0,2) = 1,9 | E84: 1.9 | F84: 0.4 | G84: 1.4 | H84: 0.01 | I84: =ROUND(PRODUCT(D84:H84),3) -> 0.011
... B92: DM-16:25,2-(0,85+3,1+3,1+0,85) = 17,3 | E92: 17.3 | F92: 0.6 | G92: 0.4 | H92: 0.01 | I92: =ROUND(PRODUCT(D92:H92),3) -> 0.042
B93: DM-17:7,8-(2,25+2,65) = 2,9 | D93: 2 | E93: 2.9 | F93: 0.5 | G93: 0.1 | H93: 0.01 | I93: =ROUND(PRODUCT(D93:H93),3) -> 0.003
B94: Móng ( theo chu vi đóng cừ) | E94: 25.25 | F94: 27.2 | G94: 0.1 | H94: 0.01 | I94: =ROUND(PRODUCT(D94:H94),3) -> 0.687
E95: 30.8 | F95: 30.4 | G95: 0.1 | H95: 0.01 | I95: =ROUND(PRODUCT(D95:H95),3) -> 0.936
B96: Đài cọc:
B97: M1 | D97: 5 | E97: 1.3 | F97: 1.3 | G97: 0.1 | H97: 0.01 | I97: =ROUND(PRODUCT(D97:H97),3) -> 0.008
B98: M2 | D98: 3 | E98: 1.3 | F98: 3.1 | G98: 0.1 | H98: 0.01 | I98: =ROUND(PRODUCT(D98:H98),3) -> 0.012
B99: M4 | D99: 2 | E99: 3.1 | F99: 3.1 | G99: 0.1 | H99: 0.01 | I99: =ROUND(PRODUCT(D99:H99),3) -> 0.019
B100: M5 | E100: 3.1 | F100: 4.5 | G100: 0.1 | H100: 0.01 | I100: =ROUND(PRODUCT(D100:H100),3) -> 0.014
B101: M6 | E101: 3.1 | F101: 4.9 | G101: 0.1 | H101: 0.01 | I101: =ROUND(PRODUCT(D101:H101),3) -> 0.015
B102: M6A | E102: 4.9 | F102: 3.1 | G102: 0.1 | H102: 0.01 | I102: =ROUND(PRODUCT(D102:H102),3) -> 0.015
B103: M8 | D103: 3 | E103: 3.1 | F103: 6.7 | G103: 0.1 | H103: 0.01 | I103: =ROUND(PRODUCT(D103:H103),3) -> 0.062
B104: M8A | E104: 4.5 | F104: 4.9 | G104: 0.1 | H104: 0.01 | I104: =ROUND(PRODUCT(D104:H104),3) -> 0.022
B105: M8A1 | E105: 4.5 | F105: 4.9 | G105: 0.1 | H105: 0.01 | I105: =ROUND(PRODUCT(D105:H105),3) -> 0.022
B106: M9 | E106: 4.9 | F106: 4.9 | G106: 0.1 | H106: 0.01 | I106: =ROUND(PRODUCT(D106:H106),3) -> 0.024
B107: M9A | E107: 4.9 | F107: 4.9 | G107: 0.1 | H107: 0.01 | I107: =ROUND(PRODUCT(D107:H107),3) -> 0.024
B108: M10 | E108: 4.5 | F108: 6.7 | G108: 0.1 | H108: 0.01 | I108: =ROUND(PRODUCT(D108:H108),3) -> 0.03
B109: M10A | E109: 3.1 | F109: 8.5 | G109: 0.1 | H109: 0.01 | I109: =ROUND(PRODUCT(D109:H109),3) -> 0.026
B110: M11 | E110: 4.5 | F110: 6.7 | G110: 0.1 | H110: 0.01 | I110: =ROUND(PRODUCT(D110:H110),3) -> 0.03
B111: M13 | E111: 4.5 | F111: 8.5 | G111: 0.1 | H111: 0.01 | I111: =ROUND(PRODUCT(D111:H111),3) -> 0.038
...

Sheet đọc số
D2: Số cần đọc: | G2: =PL03a!#REF! -> #REF!
B4: Số đọc | C4: Đọc chữ
A5: Hàng đơn vị | B5: =G5-10*G6 -> #REF! | C5: =IF(G5=0,"",IF(B5=0,"",IF(AND(B5=1,B6=1)," một",IF(AND(B5=1,B6>1)," mốt",IF(AND(B5=5,B6>0)," lăm",IF(G6=0,LOOKUP(B5,D5:D14,E5:E14),LOOKUP(B5,D5:D14,F5:F14))))))) -> #REF! | D5: 0 | E5: =IF(B5=0,""," Không") -> #REF! | F5: không | G5: =ROUND(G2,0) -> #REF!
A6: Hàng chục | B6: =G6-10*G7 -> #REF! | C6: =IF(G6=0,"",IF(AND(B6=0,B5=0),"",IF(AND(B6=0,B5>0)," lẻ",IF(AND(B6=1,G7<>0)," mười",IF(AND(B6=1,G7=0)," Mười",IF(B6>1,IF(G7=0,LOOKUP(B6,D5:D14,E5:E14),LOOKUP(B6,D5:D14,F5:F14)))))))&IF(B6>1," mươi","")) -> #REF! | D6: 1 | E6: Một | F6: một | G6: =ROUNDDOWN(G5/10,0) -> #REF!
A7: Hàng trăm | B7: =G7-10*G8 -> #REF! | C7: =IF(G7=0,"",IF(AND(B5=0,B6=0,B7=0),"",IF(AND(B7=0,B6>0)," không",IF(AND(B7=0,B5>0)," không",IF(G8=0,LOOKUP(B7,D5:D14,E5:E14),LOOKUP(B7,D5:D14,F5:F14)))))&IF(SUM(B5:B7)>0," trăm","")) -> #REF! | D7: 2 | E7: Hai | F7: hai | G7: =ROUNDDOWN(G6/10,0) -> #REF!
A8: Hàng nghìn | B8: =G8-10*G9 -> #REF! | C8: =IF(G8=0,"",IF(B8=0,"",IF(AND(B8=1,B9=1)," một",IF(AND(B8=1,B9>1)," mốt",IF(AND(B8=5,B9>0)," lăm",IF(G9=0,LOOKUP(B8,D5:D14,E5:E14),LOOKUP(B8,D5:D14,F5:F14))))))&IF(SUM(B8:B10)>0," nghìn","")) -> #REF! | D8: 3 | E8: Ba | F8: ba | G8: =ROUNDDOWN(G7/10,0) -> #REF!
A9: Hàng chục nghìn | B9: =G9-10*G10 -> #REF! | C9: =IF(G9=0,"",IF(AND(B9=0,B8=0),"",IF(AND(B9=0,B8>0)," lẻ",IF(AND(B9=1,G10<>0)," mười",IF(AND(B9=1,G10=0)," Mười",IF(B9>1,IF(G10=0,LOOKUP(B9,D5:D14,E5:E14),LOOKUP(B9,D5:D14,F5:F14)))))))&IF(B9>1," mươi","")) -> #REF! | D9: 4 | E9: Bốn | F9: bốn | G9: =ROUNDDOWN(G8/10,0) -> #REF!
A10: Hàng trăm nghìn | B10: =G10-10*G11 -> #REF! | C10: =IF(G10=0,"",IF(AND(B8=0,B9=0,B10=0),"",IF(AND(B10=0,B9>0)," không",IF(AND(B10=0,B8>0)," không",IF(G11=0,LOOKUP(B10,D5:D14,E5:E14),LOOKUP(B10,D5:D14,F5:F14)))))&IF(SUM(B8:B10)>0," trăm","")) -> #REF! | D10: 5 | E10: Năm | F10: năm | G10: =ROUNDDOWN(G9/10,0) -> #REF!
A11: Hàng triệu | B11: =G11-10*G12 -> #REF! | C11: =IF(G11=0,"",IF(B11=0,"",IF(AND(B11=1,B12=1)," một",IF(AND(B11=1,B12>1)," mốt",IF(AND(B11=5,B12>0)," lăm",IF(G12=0,LOOKUP(B11,D5:D14,E5:E14),LOOKUP(B11,D5:D14,F5:F14))))))&IF(SUM(B11:B13)>0," triệu,","")) -> #REF! | D11: 6 | E11: Sáu | F11: sáu | G11: =ROUNDDOWN(G10/10,0) -> #REF!
A12: Hàng chục triệu | B12: =G12-10*G13 -> #REF! | C12: =IF(G12=0,"",IF(AND(B12=0,B11=0),"",IF(AND(B12=0,B11>0)," lẻ",IF(AND(B12=1,G13<>0)," mười",IF(AND(B12=1,G13=0)," Mười",IF(B12>1,IF(G13=0,LOOKUP(B12,D5:D14,E5:E14),LOOKUP(B12,D5:D14,F5:F14)))))))&IF(B12>1," mươi","")) -> #REF! | D12: 7 | E12: Bảy | F12: bảy | G12: =ROUNDDOWN(G11/10,0) -> #REF!
A13: Hàng trăm triệu | B13: =G13-10*G14 -> #REF! | C13: =IF(G13=0,"",IF(AND(B11=0,B12=0,B13=0),"",IF(AND(B13=0,B12>0)," không",IF(AND(B13=0,B11>0)," không",IF(G14=0,LOOKUP(B13,D5:D14,E5:E14),LOOKUP(B13,D5:D14,F5:F14)))))&IF(SUM(B11:B13)>0," trăm","")) -> #REF! | D13: 8 | E13: Tám | F13: tám | G13: =ROUNDDOWN(G12/10,0) -> #REF!
A14: Hàng tỷ | B14: =G14-10*G15 -> #REF! | C14: =IF(G14=0,"",IF(B14=0,"",IF(AND(B14=1,B15=1)," một",IF(AND(B14=1,B15>1)," mốt",IF(AND(B14=5,B15>0)," lăm",IF(G15=0,LOOKUP(B14,D5:D14,E5:E14),LOOKUP(B14,D5:D14,F5:F14))))))&IF(SUM(B14:B20)>0," tỷ,","")) -> #REF! | D14: 9 | E14: Chín | F14: chín | G14: =ROUNDDOWN(G13/10,0) -> #REF!
A15: Hàng chục tỷ | B15: =G15-10*G16 -> #REF! | C15: =IF(G15=0,"",IF(AND(B15=0,B14=0),"",IF(AND(B15=0,B14>0)," lẻ",IF(AND(B15=1,G16<>0)," mười",IF(AND(B15=1,G16=0)," Mười",IF(B15>1,IF(G16=0,LOOKUP(B15,D5:D14,E5:E14),LOOKUP(B15,D5:D14,F5:F14)))))))&IF(B15>1," mươi","")) -> #REF! | G15: =ROUNDDOWN(G14/10,0) -> #REF!
A16: Hàng trăm tỷ | B16: =G16-10*G17 -> #REF! | C16: =IF(G16=0,"",IF(AND(B14=0,B15=0,B16=0),"",IF(AND(B16=0,B15>0)," không",IF(AND(B16=0,B14>0)," không",IF(G17=0,LOOKUP(B16,D5:D14,E5:E14),LOOKUP(B16,D5:D14,F5:F14)))))&IF(SUM(B14:B16)>0," trăm","")) -> #REF! | G16: =ROUNDDOWN(G15/10,0) -> #REF!
A17: Hàng nghìn tỷ | B17: =G17-10*G18 -> #REF! | C17: =IF(G17=0,"",IF(B17=0,"",IF(AND(B17=1,B18=1)," một",IF(AND(B17=1,B18>1)," mốt",IF(AND(B17=5,B18>0)," lăm",IF(G18=0,LOOKUP(B17,D5:D14,E5:E14),LOOKUP(B17,D5:D14,F5:F14))))))&IF(SUM(B17:B19)>0," nghìn","")) -> #REF! | G17: =ROUNDDOWN(G16/10,0) -> #REF!
A18: Hàng chục nghìn tỷ | B18: =G18-10*G19 -> #REF! | C18: =IF(G18=0,"",IF(AND(B18=0,B17=0),"",IF(AND(B18=0,B17>0)," lẻ",IF(AND(B18=1,G19<>0)," mười",IF(AND(B18=1,G19=0)," Mười",IF(B18>1,IF(G19=0,LOOKUP(B18,D5:D14,E5:E14),LOOKUP(B18,D5:D14,F5:F14)))))))&IF(B18>1," mươi","")) -> #REF! | G18: =ROUNDDOWN(G17/10,0) -> #REF!
A19: Hàng trăm nghìn tỷ | B19: =G19-10*B20 -> #REF! | C19: =IF(G19=0,"",IF(AND(B17=0,B18=0,B19=0),"",IF(AND(B19=0,B18>0)," không",IF(AND(B19=0,B17>0)," không",IF(G20=0,LOOKUP(B19,D5:D14,E5:E14),LOOKUP(B19,D5:D14,F5:F14)))))&IF(SUM(B17:B19)>0," trăm","")) -> #REF! | G19: =ROUNDDOWN(G18/10,0) -> #REF!
C20: =IF(G20=0,"",IF(B20=0,"",IF(AND(B20=1,#REF!=1)," một",IF(AND(B20=1,#REF!>1)," mốt",IF(AND(B20=5,#REF!>0)," lăm",IF(#REF!=0,LOOKUP(B20,D5:D14,E5:E14),LOOKUP(B20,D5:D14,F5:F14))))))&IF(SUM(B20:B20)>0," triệu",""))
A21: Với Font Unicode: Đọc số là:
G22: =""& IF(G5=0,"Không ",CONCATENATE(C19,C18,C17,C16,C15,C14,C13,C12,C11,C10,C9,C8,C7,C6,C5)) & " đồng" -> #REF!
A24: Với Font TCVN, VNI
B25: - Copy Vùng dữ liệu ở trên đến vị trí khác.
B26: - Thay đổi các chữ trong công thức ở vùng "C6:F20" bằng bảng mã TCVN
B27: hoặc VNI sẽ có được cách đọc tương ứng
D34: Số cần đọc: | G34: =PL03a!#REF! -> #REF!
B36: Số đọc | C36: Đọc chữ
A37: Hàng đơn vị | B37: =G37-10*G38 -> #REF! | C37: =IF(G37=0,"",IF(B37=0,"",IF(AND(B37=1,B38=1)," một",IF(AND(B37=1,B38>1)," mốt",IF(AND(B37=5,B38>0)," lăm",IF(G38=0,LOOKUP(B37,D37:D46,E37:E46),LOOKUP(B37,D37:D46,F37:F46))))))) -> #REF! | D37: 0 | E37: =IF(B37=0,""," Không") -> #REF! | F37: không | G37: =ROUND(G34,0) -> #REF!
A38: Hàng chục | B38: =G38-10*G39 -> #REF! | C38: =IF(G38=0,"",IF(AND(B38=0,B37=0),"",IF(AND(B38=0,B37>0)," lẻ",IF(AND(B38=1,G39<>0)," mười",IF(AND(B38=1,G39=0)," Mười",IF(B38>1,IF(G39=0,LOOKUP(B38,D37:D46,E37:E46),LOOKUP(B38,D37:D46,F37:F46)))))))&IF(B38>1," mươi","")) -> #REF! | D38: 1 | E38: Một | F38: một | G38: =ROUNDDOWN(G37/10,0) -> #REF!
A39: Hàng trăm | B39: =G39-10*G40 -> #REF! | C39: =IF(G39=0,"",IF(AND(B37=0,B38=0,B39=0),"",IF(AND(B39=0,B38>0)," không",IF(AND(B39=0,B37>0)," không",IF(G40=0,LOOKUP(B39,D37:D46,E37:E46),LOOKUP(B39,D37:D46,F37:F46)))))&IF(SUM(B37:B39)>0," trăm","")) -> #REF! | D39: 2 | E39: Hai | F39: hai | G39: =ROUNDDOWN(G38/10,0) -> #REF!
A40: Hàng nghìn | B40: =G40-10*G41 -> #REF! | C40: =IF(G40=0,"",IF(B40=0,"",IF(AND(B40=1,B41=1)," một",IF(AND(B40=1,B41>1)," mốt",IF(AND(B40=5,B41>0)," lăm",IF(G41=0,LOOKUP(B40,D37:D46,E37:E46),LOOKUP(B40,D37:D46,F37:F46))))))&IF(SUM(B40:B42)>0," nghìn","")) -> #REF! | D40: 3 | E40: Ba | F40: ba | G40: =ROUNDDOWN(G39/10,0) -> #REF!
A41: Hàng chục nghìn | B41: =G41-10*G42 -> #REF! | C41: =IF(G41=0,"",IF(AND(B41=0,B40=0),"",IF(AND(B41=0,B40>0)," lẻ",IF(AND(B41=1,G42<>0)," mười",IF(AND(B41=1,G42=0)," Mười",IF(B41>1,IF(G42=0,LOOKUP(B41,D37:D46,E37:E46),LOOKUP(B41,D37:D46,F37:F46)))))))&IF(B41>1," mươi","")) -> #REF! | D41: 4 | E41: Bốn | F41: bốn | G41: =ROUNDDOWN(G40/10,0) -> #REF!
A42: Hàng trăm nghìn | B42: =G42-10*G43 -> #REF! | C42: =IF(G42=0,"",IF(AND(B40=0,B41=0,B42=0),"",IF(AND(B42=0,B41>0)," không",IF(AND(B42=0,B40>0)," không",IF(G43=0,LOOKUP(B42,D37:D46,E37:E46),LOOKUP(B42,D37:D46,F37:F46)))))&IF(SUM(B40:B42)>0," trăm","")) -> #REF! | D42: 5 | E42: Năm | F42: năm | G42: =ROUNDDOWN(G41/10,0) -> #REF!
A43: Hàng triệu | B43: =G43-10*G44 -> #REF! | C43: =IF(G43=0,"",IF(B43=0,"",IF(AND(B43=1,B44=1)," một",IF(AND(B43=1,B44>1)," mốt",IF(AND(B43=5,B44>0)," lăm",IF(G44=0,LOOKUP(B43,D37:D46,E37:E46),LOOKUP(B43,D37:D46,F37:F46))))))&IF(SUM(B43:B45)>0," triệu,","")) -> #REF! | D43: 6 | E43: Sáu | F43: sáu | G43: =ROUNDDOWN(G42/10,0) -> #REF!
A44: Hàng chục triệu | B44: =G44-10*G45 -> #REF! | C44: =IF(G44=0,"",IF(AND(B44=0,B43=0),"",IF(AND(B44=0,B43>0)," lẻ",IF(AND(B44=1,G45<>0)," mười",IF(AND(B44=1,G45=0)," Mười",IF(B44>1,IF(G45=0,LOOKUP(B44,D37:D46,E37:E46),LOOKUP(B44,D37:D46,F37:F46)))))))&IF(B44>1," mươi","")) -> #REF! | D44: 7 | E44: Bảy | F44: bảy | G44: =ROUNDDOWN(G43/10,0) -> #REF!
A45: Hàng trăm triệu | B45: =G45-10*G46 -> #REF! | C45: =IF(G45=0,"",IF(AND(B43=0,B44=0,B45=0),"",IF(AND(B45=0,B44>0)," không",IF(AND(B45=0,B43>0)," không",IF(G46=0,LOOKUP(B45,D37:D46,E37:E46),LOOKUP(B45,D37:D46,F37:F46)))))&IF(SUM(B43:B45)>0," trăm","")) -> #REF! | D45: 8 | E45: Tám | F45: tám | G45: =ROUNDDOWN(G44/10,0) -> #REF!
A46: Hàng tỷ | B46: =G46-10*G47 -> #REF! | C46: =IF(G46=0,"",IF(B46=0,"",IF(AND(B46=1,B47=1)," một",IF(AND(B46=1,B47>1)," mốt",IF(AND(B46=5,B47>0)," lăm",IF(G47=0,LOOKUP(B46,D37:D46,E37:E46),LOOKUP(B46,D37:D46,F37:F46))))))&IF(SUM(B46:B52)>0," tỷ,","")) -> #REF! | D46: 9 | E46: Chín | F46: chín | G46: =ROUNDDOWN(G45/10,0) -> #REF!
A47: Hàng chục tỷ | B47: =G47-10*G48 -> #REF! | C47: =IF(G47=0,"",IF(AND(B47=0,B46=0),"",IF(AND(B47=0,B46>0)," lẻ",IF(AND(B47=1,G48<>0)," mười",IF(AND(B47=1,G48=0)," Mười",IF(B47>1,IF(G48=0,LOOKUP(B47,D37:D46,E37:E46),LOOKUP(B47,D37:D46,F37:F46)))))))&IF(B47>1," mươi","")) -> #REF! | G47: =ROUNDDOWN(G46/10,0) -> #REF!
A48: Hàng trăm tỷ | B48: =G48-10*G49 -> #REF! | C48: =IF(G48=0,"",IF(AND(B46=0,B47=0,B48=0),"",IF(AND(B48=0,B47>0)," không",IF(AND(B48=0,B46>0)," không",IF(G49=0,LOOKUP(B48,D37:D46,E37:E46),LOOKUP(B48,D37:D46,F37:F46)))))&IF(SUM(B46:B48)>0," trăm","")) -> #REF! | G48: =ROUNDDOWN(G47/10,0) -> #REF!
A49: Hàng nghìn tỷ | B49: =G49-10*G50 -> #REF! | C49: =IF(G49=0,"",IF(B49=0,"",IF(AND(B49=1,B50=1)," một",IF(AND(B49=1,B50>1)," mốt",IF(AND(B49=5,B50>0)," lăm",IF(G50=0,LOOKUP(B49,D37:D46,E37:E46),LOOKUP(B49,D37:D46,F37:F46))))))&IF(SUM(B49:B51)>0," nghìn","")) -> #REF! | G49: =ROUNDDOWN(G48/10,0) -> #REF!
A50: Hàng chục nghìn tỷ | B50: =G50-10*G51 -> #REF! | C50: =IF(G50=0,"",IF(AND(B50=0,B49=0),"",IF(AND(B50=0,B49>0)," lẻ",IF(AND(B50=1,G51<>0)," mười",IF(AND(B50=1,G51=0)," Mười",IF(B50>1,IF(G51=0,LOOKUP(B50,D37:D46,E37:E46),LOOKUP(B50,D37:D46,F37:F46)))))))&IF(B50>1," mươi","")) -> #REF! | G50: =ROUNDDOWN(G49/10,0) -> #REF!
A51: Hàng trăm nghìn tỷ | B51: =G51-10*B52 -> #REF! | C51: =IF(G51=0,"",IF(AND(B49=0,B50=0,B51=0),"",IF(AND(B51=0,B50>0)," không",IF(AND(B51=0,B49>0)," không",IF(G52=0,LOOKUP(B51,D37:D46,E37:E46),LOOKUP(B51,D37:D46,F37:F46)))))&IF(SUM(B49:B51)>0," trăm","")) -> #REF! | G51: =ROUNDDOWN(G50/10,0) -> #REF!
C52: =IF(G52=0,"",IF(B52=0,"",IF(AND(B52=1,#REF!=1)," một",IF(AND(B52=1,#REF!>1)," mốt",IF(AND(B52=5,#REF!>0)," lăm",IF(#REF!=0,LOOKUP(B52,D37:D46,E37:E46),LOOKUP(B52,D37:D46,F37:F46))))))&IF(SUM(B52:B52)>0," triệu",""))
A53: Với Font Unicode: Đọc số là:
G54: =""& IF(G37=0,"Không ",CONCATENATE(C51,C50,C49,C48,C47,C46,C45,C44,C43,C42,C41,C40,C39,C38,C37)) & " đồng" -> #REF!
A56: Với Font TCVN, VNI
B57: - Copy Vùng dữ liệu ở trên đến vị trí khác.
B58: - Thay đổi các chữ trong công thức ở vùng "C6:F20" bằng bảng mã TCVN
B59: hoặc VNI sẽ có được cách đọc tương ứng
